aiobotocore-stubs/__init__.pyi
aiobotocore-stubs/args.pyi
aiobotocore-stubs/awsrequest.pyi
aiobotocore-stubs/client.pyi
aiobotocore-stubs/config.pyi
aiobotocore-stubs/configprovider.pyi
aiobotocore-stubs/context.pyi
aiobotocore-stubs/credentials.pyi
aiobotocore-stubs/discovery.pyi
aiobotocore-stubs/endpoint.pyi
aiobotocore-stubs/eventstream.pyi
aiobotocore-stubs/handlers.pyi
aiobotocore-stubs/hooks.pyi
aiobotocore-stubs/httpchecksum.pyi
aiobotocore-stubs/httpsession.pyi
aiobotocore-stubs/httpxsession.pyi
aiobotocore-stubs/paginate.pyi
aiobotocore-stubs/parsers.pyi
aiobotocore-stubs/py.typed
aiobotocore-stubs/regions.pyi
aiobotocore-stubs/response.pyi
aiobotocore-stubs/retryhandler.pyi
aiobotocore-stubs/session.pyi
aiobotocore-stubs/signers.pyi
aiobotocore-stubs/stub.pyi
aiobotocore-stubs/tokens.pyi
aiobotocore-stubs/utils.pyi
aiobotocore-stubs/waiter.pyi
aiobotocore-stubs/retries/__init__.pyi
aiobotocore-stubs/retries/adaptive.pyi
aiobotocore-stubs/retries/bucket.pyi
aiobotocore-stubs/retries/special.pyi
aiobotocore-stubs/retries/standard.pyi
types_aiobotocore-3.1.1.dist-info/licenses/LICENSE
types_aiobotocore-3.1.1.dist-info/METADATA
types_aiobotocore-3.1.1.dist-info/WHEEL
types_aiobotocore-3.1.1.dist-info/top_level.txt
types_aiobotocore-3.1.1.dist-info/RECORD
