Metadata-Version: 2.4
Name: types-aiobotocore
Version: 3.1.1
Summary: Type annotations for aiobotocore 3.1.1 generated with mypy-boto3-builder 8.12.0
Author-email: Vlad Emelianov <vlad.emelianov.nz@gmail.com>
License-Expression: MIT
Project-URL: Homepage, https://github.com/youtype/mypy_boto3_builder
Project-URL: Documentation, https://youtype.github.io/types_aiobotocore_docs/
Project-URL: Source, https://github.com/youtype/mypy_boto3_builder
Project-URL: Tracker, https://github.com/youtype/mypy_boto3_builder/issues
Keywords: aiobotocore,aiobotocore-stubs,type-annotations,mypy,typeshed,autocomplete
Platform: any
Classifier: Development Status :: 5 - Production/Stable
Classifier: Intended Audience :: Developers
Classifier: Environment :: Console
Classifier: Natural Language :: English
Classifier: Operating System :: OS Independent
Classifier: Programming Language :: Python :: 3
Classifier: Programming Language :: Python :: 3.9
Classifier: Programming Language :: Python :: 3.10
Classifier: Programming Language :: Python :: 3.11
Classifier: Programming Language :: Python :: 3.12
Classifier: Programming Language :: Python :: 3.13
Classifier: Programming Language :: Python :: 3.14
Classifier: Programming Language :: Python :: 3 :: Only
Classifier: Programming Language :: Python :: Implementation :: CPython
Classifier: Typing :: Stubs Only
Requires-Python: >=3.9
License-File: LICENSE
Requires-Dist: botocore-stubs
Requires-Dist: typing-extensions>=4.1.0; python_version < "3.12"
Provides-Extra: full
Requires-Dist: types-aiobotocore-full<3.2.0,>=3.1.0; extra == "full"
Provides-Extra: aiobotocore
Requires-Dist: aiobotocore==3.1.1; extra == "aiobotocore"
Provides-Extra: all
Requires-Dist: types-aiobotocore-accessanalyzer<3.2.0,>=3.1.0; extra == "all"
Requires-Dist: types-aiobotocore-account<3.2.0,>=3.1.0; extra == "all"
Requires-Dist: types-aiobotocore-acm<3.2.0,>=3.1.0; extra == "all"
Requires-Dist: types-aiobotocore-acm-pca<3.2.0,>=3.1.0; extra == "all"
Requires-Dist: types-aiobotocore-aiops<3.2.0,>=3.1.0; extra == "all"
Requires-Dist: types-aiobotocore-amp<3.2.0,>=3.1.0; extra == "all"
Requires-Dist: types-aiobotocore-amplify<3.2.0,>=3.1.0; extra == "all"
Requires-Dist: types-aiobotocore-amplifybackend<3.2.0,>=3.1.0; extra == "all"
Requires-Dist: types-aiobotocore-amplifyuibuilder<3.2.0,>=3.1.0; extra == "all"
Requires-Dist: types-aiobotocore-apigateway<3.2.0,>=3.1.0; extra == "all"
Requires-Dist: types-aiobotocore-apigatewaymanagementapi<3.2.0,>=3.1.0; extra == "all"
Requires-Dist: types-aiobotocore-apigatewayv2<3.2.0,>=3.1.0; extra == "all"
Requires-Dist: types-aiobotocore-appconfig<3.2.0,>=3.1.0; extra == "all"
Requires-Dist: types-aiobotocore-appconfigdata<3.2.0,>=3.1.0; extra == "all"
Requires-Dist: types-aiobotocore-appfabric<3.2.0,>=3.1.0; extra == "all"
Requires-Dist: types-aiobotocore-appflow<3.2.0,>=3.1.0; extra == "all"
Requires-Dist: types-aiobotocore-appintegrations<3.2.0,>=3.1.0; extra == "all"
Requires-Dist: types-aiobotocore-application-autoscaling<3.2.0,>=3.1.0; extra == "all"
Requires-Dist: types-aiobotocore-application-insights<3.2.0,>=3.1.0; extra == "all"
Requires-Dist: types-aiobotocore-application-signals<3.2.0,>=3.1.0; extra == "all"
Requires-Dist: types-aiobotocore-applicationcostprofiler<3.2.0,>=3.1.0; extra == "all"
Requires-Dist: types-aiobotocore-appmesh<3.2.0,>=3.1.0; extra == "all"
Requires-Dist: types-aiobotocore-apprunner<3.2.0,>=3.1.0; extra == "all"
Requires-Dist: types-aiobotocore-appstream<3.2.0,>=3.1.0; extra == "all"
Requires-Dist: types-aiobotocore-appsync<3.2.0,>=3.1.0; extra == "all"
Requires-Dist: types-aiobotocore-arc-region-switch<3.2.0,>=3.1.0; extra == "all"
Requires-Dist: types-aiobotocore-arc-zonal-shift<3.2.0,>=3.1.0; extra == "all"
Requires-Dist: types-aiobotocore-artifact<3.2.0,>=3.1.0; extra == "all"
Requires-Dist: types-aiobotocore-athena<3.2.0,>=3.1.0; extra == "all"
Requires-Dist: types-aiobotocore-auditmanager<3.2.0,>=3.1.0; extra == "all"
Requires-Dist: types-aiobotocore-autoscaling<3.2.0,>=3.1.0; extra == "all"
Requires-Dist: types-aiobotocore-autoscaling-plans<3.2.0,>=3.1.0; extra == "all"
Requires-Dist: types-aiobotocore-b2bi<3.2.0,>=3.1.0; extra == "all"
Requires-Dist: types-aiobotocore-backup<3.2.0,>=3.1.0; extra == "all"
Requires-Dist: types-aiobotocore-backup-gateway<3.2.0,>=3.1.0; extra == "all"
Requires-Dist: types-aiobotocore-backupsearch<3.2.0,>=3.1.0; extra == "all"
Requires-Dist: types-aiobotocore-batch<3.2.0,>=3.1.0; extra == "all"
Requires-Dist: types-aiobotocore-bcm-dashboards<3.2.0,>=3.1.0; extra == "all"
Requires-Dist: types-aiobotocore-bcm-data-exports<3.2.0,>=3.1.0; extra == "all"
Requires-Dist: types-aiobotocore-bcm-pricing-calculator<3.2.0,>=3.1.0; extra == "all"
Requires-Dist: types-aiobotocore-bcm-recommended-actions<3.2.0,>=3.1.0; extra == "all"
Requires-Dist: types-aiobotocore-bedrock<3.2.0,>=3.1.0; extra == "all"
Requires-Dist: types-aiobotocore-bedrock-agent<3.2.0,>=3.1.0; extra == "all"
Requires-Dist: types-aiobotocore-bedrock-agent-runtime<3.2.0,>=3.1.0; extra == "all"
Requires-Dist: types-aiobotocore-bedrock-agentcore<3.2.0,>=3.1.0; extra == "all"
Requires-Dist: types-aiobotocore-bedrock-agentcore-control<3.2.0,>=3.1.0; extra == "all"
Requires-Dist: types-aiobotocore-bedrock-data-automation<3.2.0,>=3.1.0; extra == "all"
Requires-Dist: types-aiobotocore-bedrock-data-automation-runtime<3.2.0,>=3.1.0; extra == "all"
Requires-Dist: types-aiobotocore-bedrock-runtime<3.2.0,>=3.1.0; extra == "all"
Requires-Dist: types-aiobotocore-billing<3.2.0,>=3.1.0; extra == "all"
Requires-Dist: types-aiobotocore-billingconductor<3.2.0,>=3.1.0; extra == "all"
Requires-Dist: types-aiobotocore-braket<3.2.0,>=3.1.0; extra == "all"
Requires-Dist: types-aiobotocore-budgets<3.2.0,>=3.1.0; extra == "all"
Requires-Dist: types-aiobotocore-ce<3.2.0,>=3.1.0; extra == "all"
Requires-Dist: types-aiobotocore-chatbot<3.2.0,>=3.1.0; extra == "all"
Requires-Dist: types-aiobotocore-chime<3.2.0,>=3.1.0; extra == "all"
Requires-Dist: types-aiobotocore-chime-sdk-identity<3.2.0,>=3.1.0; extra == "all"
Requires-Dist: types-aiobotocore-chime-sdk-media-pipelines<3.2.0,>=3.1.0; extra == "all"
Requires-Dist: types-aiobotocore-chime-sdk-meetings<3.2.0,>=3.1.0; extra == "all"
Requires-Dist: types-aiobotocore-chime-sdk-messaging<3.2.0,>=3.1.0; extra == "all"
Requires-Dist: types-aiobotocore-chime-sdk-voice<3.2.0,>=3.1.0; extra == "all"
Requires-Dist: types-aiobotocore-cleanrooms<3.2.0,>=3.1.0; extra == "all"
Requires-Dist: types-aiobotocore-cleanroomsml<3.2.0,>=3.1.0; extra == "all"
Requires-Dist: types-aiobotocore-cloud9<3.2.0,>=3.1.0; extra == "all"
Requires-Dist: types-aiobotocore-cloudcontrol<3.2.0,>=3.1.0; extra == "all"
Requires-Dist: types-aiobotocore-clouddirectory<3.2.0,>=3.1.0; extra == "all"
Requires-Dist: types-aiobotocore-cloudformation<3.2.0,>=3.1.0; extra == "all"
Requires-Dist: types-aiobotocore-cloudfront<3.2.0,>=3.1.0; extra == "all"
Requires-Dist: types-aiobotocore-cloudfront-keyvaluestore<3.2.0,>=3.1.0; extra == "all"
Requires-Dist: types-aiobotocore-cloudhsm<3.2.0,>=3.1.0; extra == "all"
Requires-Dist: types-aiobotocore-cloudhsmv2<3.2.0,>=3.1.0; extra == "all"
Requires-Dist: types-aiobotocore-cloudsearch<3.2.0,>=3.1.0; extra == "all"
Requires-Dist: types-aiobotocore-cloudsearchdomain<3.2.0,>=3.1.0; extra == "all"
Requires-Dist: types-aiobotocore-cloudtrail<3.2.0,>=3.1.0; extra == "all"
Requires-Dist: types-aiobotocore-cloudtrail-data<3.2.0,>=3.1.0; extra == "all"
Requires-Dist: types-aiobotocore-cloudwatch<3.2.0,>=3.1.0; extra == "all"
Requires-Dist: types-aiobotocore-codeartifact<3.2.0,>=3.1.0; extra == "all"
Requires-Dist: types-aiobotocore-codebuild<3.2.0,>=3.1.0; extra == "all"
Requires-Dist: types-aiobotocore-codecatalyst<3.2.0,>=3.1.0; extra == "all"
Requires-Dist: types-aiobotocore-codecommit<3.2.0,>=3.1.0; extra == "all"
Requires-Dist: types-aiobotocore-codeconnections<3.2.0,>=3.1.0; extra == "all"
Requires-Dist: types-aiobotocore-codedeploy<3.2.0,>=3.1.0; extra == "all"
Requires-Dist: types-aiobotocore-codeguru-reviewer<3.2.0,>=3.1.0; extra == "all"
Requires-Dist: types-aiobotocore-codeguru-security<3.2.0,>=3.1.0; extra == "all"
Requires-Dist: types-aiobotocore-codeguruprofiler<3.2.0,>=3.1.0; extra == "all"
Requires-Dist: types-aiobotocore-codepipeline<3.2.0,>=3.1.0; extra == "all"
Requires-Dist: types-aiobotocore-codestar-connections<3.2.0,>=3.1.0; extra == "all"
Requires-Dist: types-aiobotocore-codestar-notifications<3.2.0,>=3.1.0; extra == "all"
Requires-Dist: types-aiobotocore-cognito-identity<3.2.0,>=3.1.0; extra == "all"
Requires-Dist: types-aiobotocore-cognito-idp<3.2.0,>=3.1.0; extra == "all"
Requires-Dist: types-aiobotocore-cognito-sync<3.2.0,>=3.1.0; extra == "all"
Requires-Dist: types-aiobotocore-comprehend<3.2.0,>=3.1.0; extra == "all"
Requires-Dist: types-aiobotocore-comprehendmedical<3.2.0,>=3.1.0; extra == "all"
Requires-Dist: types-aiobotocore-compute-optimizer<3.2.0,>=3.1.0; extra == "all"
Requires-Dist: types-aiobotocore-compute-optimizer-automation<3.2.0,>=3.1.0; extra == "all"
Requires-Dist: types-aiobotocore-config<3.2.0,>=3.1.0; extra == "all"
Requires-Dist: types-aiobotocore-connect<3.2.0,>=3.1.0; extra == "all"
Requires-Dist: types-aiobotocore-connect-contact-lens<3.2.0,>=3.1.0; extra == "all"
Requires-Dist: types-aiobotocore-connectcampaigns<3.2.0,>=3.1.0; extra == "all"
Requires-Dist: types-aiobotocore-connectcampaignsv2<3.2.0,>=3.1.0; extra == "all"
Requires-Dist: types-aiobotocore-connectcases<3.2.0,>=3.1.0; extra == "all"
Requires-Dist: types-aiobotocore-connectparticipant<3.2.0,>=3.1.0; extra == "all"
Requires-Dist: types-aiobotocore-controlcatalog<3.2.0,>=3.1.0; extra == "all"
Requires-Dist: types-aiobotocore-controltower<3.2.0,>=3.1.0; extra == "all"
Requires-Dist: types-aiobotocore-cost-optimization-hub<3.2.0,>=3.1.0; extra == "all"
Requires-Dist: types-aiobotocore-cur<3.2.0,>=3.1.0; extra == "all"
Requires-Dist: types-aiobotocore-customer-profiles<3.2.0,>=3.1.0; extra == "all"
Requires-Dist: types-aiobotocore-databrew<3.2.0,>=3.1.0; extra == "all"
Requires-Dist: types-aiobotocore-dataexchange<3.2.0,>=3.1.0; extra == "all"
Requires-Dist: types-aiobotocore-datapipeline<3.2.0,>=3.1.0; extra == "all"
Requires-Dist: types-aiobotocore-datasync<3.2.0,>=3.1.0; extra == "all"
Requires-Dist: types-aiobotocore-datazone<3.2.0,>=3.1.0; extra == "all"
Requires-Dist: types-aiobotocore-dax<3.2.0,>=3.1.0; extra == "all"
Requires-Dist: types-aiobotocore-deadline<3.2.0,>=3.1.0; extra == "all"
Requires-Dist: types-aiobotocore-detective<3.2.0,>=3.1.0; extra == "all"
Requires-Dist: types-aiobotocore-devicefarm<3.2.0,>=3.1.0; extra == "all"
Requires-Dist: types-aiobotocore-devops-guru<3.2.0,>=3.1.0; extra == "all"
Requires-Dist: types-aiobotocore-directconnect<3.2.0,>=3.1.0; extra == "all"
Requires-Dist: types-aiobotocore-discovery<3.2.0,>=3.1.0; extra == "all"
Requires-Dist: types-aiobotocore-dlm<3.2.0,>=3.1.0; extra == "all"
Requires-Dist: types-aiobotocore-dms<3.2.0,>=3.1.0; extra == "all"
Requires-Dist: types-aiobotocore-docdb<3.2.0,>=3.1.0; extra == "all"
Requires-Dist: types-aiobotocore-docdb-elastic<3.2.0,>=3.1.0; extra == "all"
Requires-Dist: types-aiobotocore-drs<3.2.0,>=3.1.0; extra == "all"
Requires-Dist: types-aiobotocore-ds<3.2.0,>=3.1.0; extra == "all"
Requires-Dist: types-aiobotocore-ds-data<3.2.0,>=3.1.0; extra == "all"
Requires-Dist: types-aiobotocore-dsql<3.2.0,>=3.1.0; extra == "all"
Requires-Dist: types-aiobotocore-dynamodb<3.2.0,>=3.1.0; extra == "all"
Requires-Dist: types-aiobotocore-dynamodbstreams<3.2.0,>=3.1.0; extra == "all"
Requires-Dist: types-aiobotocore-ebs<3.2.0,>=3.1.0; extra == "all"
Requires-Dist: types-aiobotocore-ec2<3.2.0,>=3.1.0; extra == "all"
Requires-Dist: types-aiobotocore-ec2-instance-connect<3.2.0,>=3.1.0; extra == "all"
Requires-Dist: types-aiobotocore-ecr<3.2.0,>=3.1.0; extra == "all"
Requires-Dist: types-aiobotocore-ecr-public<3.2.0,>=3.1.0; extra == "all"
Requires-Dist: types-aiobotocore-ecs<3.2.0,>=3.1.0; extra == "all"
Requires-Dist: types-aiobotocore-efs<3.2.0,>=3.1.0; extra == "all"
Requires-Dist: types-aiobotocore-eks<3.2.0,>=3.1.0; extra == "all"
Requires-Dist: types-aiobotocore-eks-auth<3.2.0,>=3.1.0; extra == "all"
Requires-Dist: types-aiobotocore-elasticache<3.2.0,>=3.1.0; extra == "all"
Requires-Dist: types-aiobotocore-elasticbeanstalk<3.2.0,>=3.1.0; extra == "all"
Requires-Dist: types-aiobotocore-elb<3.2.0,>=3.1.0; extra == "all"
Requires-Dist: types-aiobotocore-elbv2<3.2.0,>=3.1.0; extra == "all"
Requires-Dist: types-aiobotocore-emr<3.2.0,>=3.1.0; extra == "all"
Requires-Dist: types-aiobotocore-emr-containers<3.2.0,>=3.1.0; extra == "all"
Requires-Dist: types-aiobotocore-emr-serverless<3.2.0,>=3.1.0; extra == "all"
Requires-Dist: types-aiobotocore-entityresolution<3.2.0,>=3.1.0; extra == "all"
Requires-Dist: types-aiobotocore-es<3.2.0,>=3.1.0; extra == "all"
Requires-Dist: types-aiobotocore-events<3.2.0,>=3.1.0; extra == "all"
Requires-Dist: types-aiobotocore-evidently<3.2.0,>=3.1.0; extra == "all"
Requires-Dist: types-aiobotocore-evs<3.2.0,>=3.1.0; extra == "all"
Requires-Dist: types-aiobotocore-finspace<3.2.0,>=3.1.0; extra == "all"
Requires-Dist: types-aiobotocore-finspace-data<3.2.0,>=3.1.0; extra == "all"
Requires-Dist: types-aiobotocore-firehose<3.2.0,>=3.1.0; extra == "all"
Requires-Dist: types-aiobotocore-fis<3.2.0,>=3.1.0; extra == "all"
Requires-Dist: types-aiobotocore-fms<3.2.0,>=3.1.0; extra == "all"
Requires-Dist: types-aiobotocore-forecast<3.2.0,>=3.1.0; extra == "all"
Requires-Dist: types-aiobotocore-forecastquery<3.2.0,>=3.1.0; extra == "all"
Requires-Dist: types-aiobotocore-frauddetector<3.2.0,>=3.1.0; extra == "all"
Requires-Dist: types-aiobotocore-freetier<3.2.0,>=3.1.0; extra == "all"
Requires-Dist: types-aiobotocore-fsx<3.2.0,>=3.1.0; extra == "all"
Requires-Dist: types-aiobotocore-gamelift<3.2.0,>=3.1.0; extra == "all"
Requires-Dist: types-aiobotocore-gameliftstreams<3.2.0,>=3.1.0; extra == "all"
Requires-Dist: types-aiobotocore-geo-maps<3.2.0,>=3.1.0; extra == "all"
Requires-Dist: types-aiobotocore-geo-places<3.2.0,>=3.1.0; extra == "all"
Requires-Dist: types-aiobotocore-geo-routes<3.2.0,>=3.1.0; extra == "all"
Requires-Dist: types-aiobotocore-glacier<3.2.0,>=3.1.0; extra == "all"
Requires-Dist: types-aiobotocore-globalaccelerator<3.2.0,>=3.1.0; extra == "all"
Requires-Dist: types-aiobotocore-glue<3.2.0,>=3.1.0; extra == "all"
Requires-Dist: types-aiobotocore-grafana<3.2.0,>=3.1.0; extra == "all"
Requires-Dist: types-aiobotocore-greengrass<3.2.0,>=3.1.0; extra == "all"
Requires-Dist: types-aiobotocore-greengrassv2<3.2.0,>=3.1.0; extra == "all"
Requires-Dist: types-aiobotocore-groundstation<3.2.0,>=3.1.0; extra == "all"
Requires-Dist: types-aiobotocore-guardduty<3.2.0,>=3.1.0; extra == "all"
Requires-Dist: types-aiobotocore-health<3.2.0,>=3.1.0; extra == "all"
Requires-Dist: types-aiobotocore-healthlake<3.2.0,>=3.1.0; extra == "all"
Requires-Dist: types-aiobotocore-iam<3.2.0,>=3.1.0; extra == "all"
Requires-Dist: types-aiobotocore-identitystore<3.2.0,>=3.1.0; extra == "all"
Requires-Dist: types-aiobotocore-imagebuilder<3.2.0,>=3.1.0; extra == "all"
Requires-Dist: types-aiobotocore-importexport<3.2.0,>=3.1.0; extra == "all"
Requires-Dist: types-aiobotocore-inspector<3.2.0,>=3.1.0; extra == "all"
Requires-Dist: types-aiobotocore-inspector-scan<3.2.0,>=3.1.0; extra == "all"
Requires-Dist: types-aiobotocore-inspector2<3.2.0,>=3.1.0; extra == "all"
Requires-Dist: types-aiobotocore-internetmonitor<3.2.0,>=3.1.0; extra == "all"
Requires-Dist: types-aiobotocore-invoicing<3.2.0,>=3.1.0; extra == "all"
Requires-Dist: types-aiobotocore-iot<3.2.0,>=3.1.0; extra == "all"
Requires-Dist: types-aiobotocore-iot-data<3.2.0,>=3.1.0; extra == "all"
Requires-Dist: types-aiobotocore-iot-jobs-data<3.2.0,>=3.1.0; extra == "all"
Requires-Dist: types-aiobotocore-iot-managed-integrations<3.2.0,>=3.1.0; extra == "all"
Requires-Dist: types-aiobotocore-iotanalytics<3.2.0,>=3.1.0; extra == "all"
Requires-Dist: types-aiobotocore-iotdeviceadvisor<3.2.0,>=3.1.0; extra == "all"
Requires-Dist: types-aiobotocore-iotevents<3.2.0,>=3.1.0; extra == "all"
Requires-Dist: types-aiobotocore-iotevents-data<3.2.0,>=3.1.0; extra == "all"
Requires-Dist: types-aiobotocore-iotfleetwise<3.2.0,>=3.1.0; extra == "all"
Requires-Dist: types-aiobotocore-iotsecuretunneling<3.2.0,>=3.1.0; extra == "all"
Requires-Dist: types-aiobotocore-iotsitewise<3.2.0,>=3.1.0; extra == "all"
Requires-Dist: types-aiobotocore-iotthingsgraph<3.2.0,>=3.1.0; extra == "all"
Requires-Dist: types-aiobotocore-iottwinmaker<3.2.0,>=3.1.0; extra == "all"
Requires-Dist: types-aiobotocore-iotwireless<3.2.0,>=3.1.0; extra == "all"
Requires-Dist: types-aiobotocore-ivs<3.2.0,>=3.1.0; extra == "all"
Requires-Dist: types-aiobotocore-ivs-realtime<3.2.0,>=3.1.0; extra == "all"
Requires-Dist: types-aiobotocore-ivschat<3.2.0,>=3.1.0; extra == "all"
Requires-Dist: types-aiobotocore-kafka<3.2.0,>=3.1.0; extra == "all"
Requires-Dist: types-aiobotocore-kafkaconnect<3.2.0,>=3.1.0; extra == "all"
Requires-Dist: types-aiobotocore-kendra<3.2.0,>=3.1.0; extra == "all"
Requires-Dist: types-aiobotocore-kendra-ranking<3.2.0,>=3.1.0; extra == "all"
Requires-Dist: types-aiobotocore-keyspaces<3.2.0,>=3.1.0; extra == "all"
Requires-Dist: types-aiobotocore-keyspacesstreams<3.2.0,>=3.1.0; extra == "all"
Requires-Dist: types-aiobotocore-kinesis<3.2.0,>=3.1.0; extra == "all"
Requires-Dist: types-aiobotocore-kinesis-video-archived-media<3.2.0,>=3.1.0; extra == "all"
Requires-Dist: types-aiobotocore-kinesis-video-media<3.2.0,>=3.1.0; extra == "all"
Requires-Dist: types-aiobotocore-kinesis-video-signaling<3.2.0,>=3.1.0; extra == "all"
Requires-Dist: types-aiobotocore-kinesis-video-webrtc-storage<3.2.0,>=3.1.0; extra == "all"
Requires-Dist: types-aiobotocore-kinesisanalytics<3.2.0,>=3.1.0; extra == "all"
Requires-Dist: types-aiobotocore-kinesisanalyticsv2<3.2.0,>=3.1.0; extra == "all"
Requires-Dist: types-aiobotocore-kinesisvideo<3.2.0,>=3.1.0; extra == "all"
Requires-Dist: types-aiobotocore-kms<3.2.0,>=3.1.0; extra == "all"
Requires-Dist: types-aiobotocore-lakeformation<3.2.0,>=3.1.0; extra == "all"
Requires-Dist: types-aiobotocore-lambda<3.2.0,>=3.1.0; extra == "all"
Requires-Dist: types-aiobotocore-launch-wizard<3.2.0,>=3.1.0; extra == "all"
Requires-Dist: types-aiobotocore-lex-models<3.2.0,>=3.1.0; extra == "all"
Requires-Dist: types-aiobotocore-lex-runtime<3.2.0,>=3.1.0; extra == "all"
Requires-Dist: types-aiobotocore-lexv2-models<3.2.0,>=3.1.0; extra == "all"
Requires-Dist: types-aiobotocore-lexv2-runtime<3.2.0,>=3.1.0; extra == "all"
Requires-Dist: types-aiobotocore-license-manager<3.2.0,>=3.1.0; extra == "all"
Requires-Dist: types-aiobotocore-license-manager-linux-subscriptions<3.2.0,>=3.1.0; extra == "all"
Requires-Dist: types-aiobotocore-license-manager-user-subscriptions<3.2.0,>=3.1.0; extra == "all"
Requires-Dist: types-aiobotocore-lightsail<3.2.0,>=3.1.0; extra == "all"
Requires-Dist: types-aiobotocore-location<3.2.0,>=3.1.0; extra == "all"
Requires-Dist: types-aiobotocore-logs<3.2.0,>=3.1.0; extra == "all"
Requires-Dist: types-aiobotocore-lookoutequipment<3.2.0,>=3.1.0; extra == "all"
Requires-Dist: types-aiobotocore-m2<3.2.0,>=3.1.0; extra == "all"
Requires-Dist: types-aiobotocore-machinelearning<3.2.0,>=3.1.0; extra == "all"
Requires-Dist: types-aiobotocore-macie2<3.2.0,>=3.1.0; extra == "all"
Requires-Dist: types-aiobotocore-mailmanager<3.2.0,>=3.1.0; extra == "all"
Requires-Dist: types-aiobotocore-managedblockchain<3.2.0,>=3.1.0; extra == "all"
Requires-Dist: types-aiobotocore-managedblockchain-query<3.2.0,>=3.1.0; extra == "all"
Requires-Dist: types-aiobotocore-marketplace-agreement<3.2.0,>=3.1.0; extra == "all"
Requires-Dist: types-aiobotocore-marketplace-catalog<3.2.0,>=3.1.0; extra == "all"
Requires-Dist: types-aiobotocore-marketplace-deployment<3.2.0,>=3.1.0; extra == "all"
Requires-Dist: types-aiobotocore-marketplace-entitlement<3.2.0,>=3.1.0; extra == "all"
Requires-Dist: types-aiobotocore-marketplace-reporting<3.2.0,>=3.1.0; extra == "all"
Requires-Dist: types-aiobotocore-marketplacecommerceanalytics<3.2.0,>=3.1.0; extra == "all"
Requires-Dist: types-aiobotocore-mediaconnect<3.2.0,>=3.1.0; extra == "all"
Requires-Dist: types-aiobotocore-mediaconvert<3.2.0,>=3.1.0; extra == "all"
Requires-Dist: types-aiobotocore-medialive<3.2.0,>=3.1.0; extra == "all"
Requires-Dist: types-aiobotocore-mediapackage<3.2.0,>=3.1.0; extra == "all"
Requires-Dist: types-aiobotocore-mediapackage-vod<3.2.0,>=3.1.0; extra == "all"
Requires-Dist: types-aiobotocore-mediapackagev2<3.2.0,>=3.1.0; extra == "all"
Requires-Dist: types-aiobotocore-mediastore<3.2.0,>=3.1.0; extra == "all"
Requires-Dist: types-aiobotocore-mediastore-data<3.2.0,>=3.1.0; extra == "all"
Requires-Dist: types-aiobotocore-mediatailor<3.2.0,>=3.1.0; extra == "all"
Requires-Dist: types-aiobotocore-medical-imaging<3.2.0,>=3.1.0; extra == "all"
Requires-Dist: types-aiobotocore-memorydb<3.2.0,>=3.1.0; extra == "all"
Requires-Dist: types-aiobotocore-meteringmarketplace<3.2.0,>=3.1.0; extra == "all"
Requires-Dist: types-aiobotocore-mgh<3.2.0,>=3.1.0; extra == "all"
Requires-Dist: types-aiobotocore-mgn<3.2.0,>=3.1.0; extra == "all"
Requires-Dist: types-aiobotocore-migration-hub-refactor-spaces<3.2.0,>=3.1.0; extra == "all"
Requires-Dist: types-aiobotocore-migrationhub-config<3.2.0,>=3.1.0; extra == "all"
Requires-Dist: types-aiobotocore-migrationhuborchestrator<3.2.0,>=3.1.0; extra == "all"
Requires-Dist: types-aiobotocore-migrationhubstrategy<3.2.0,>=3.1.0; extra == "all"
Requires-Dist: types-aiobotocore-mpa<3.2.0,>=3.1.0; extra == "all"
Requires-Dist: types-aiobotocore-mq<3.2.0,>=3.1.0; extra == "all"
Requires-Dist: types-aiobotocore-mturk<3.2.0,>=3.1.0; extra == "all"
Requires-Dist: types-aiobotocore-mwaa<3.2.0,>=3.1.0; extra == "all"
Requires-Dist: types-aiobotocore-mwaa-serverless<3.2.0,>=3.1.0; extra == "all"
Requires-Dist: types-aiobotocore-neptune<3.2.0,>=3.1.0; extra == "all"
Requires-Dist: types-aiobotocore-neptune-graph<3.2.0,>=3.1.0; extra == "all"
Requires-Dist: types-aiobotocore-neptunedata<3.2.0,>=3.1.0; extra == "all"
Requires-Dist: types-aiobotocore-network-firewall<3.2.0,>=3.1.0; extra == "all"
Requires-Dist: types-aiobotocore-networkflowmonitor<3.2.0,>=3.1.0; extra == "all"
Requires-Dist: types-aiobotocore-networkmanager<3.2.0,>=3.1.0; extra == "all"
Requires-Dist: types-aiobotocore-networkmonitor<3.2.0,>=3.1.0; extra == "all"
Requires-Dist: types-aiobotocore-notifications<3.2.0,>=3.1.0; extra == "all"
Requires-Dist: types-aiobotocore-notificationscontacts<3.2.0,>=3.1.0; extra == "all"
Requires-Dist: types-aiobotocore-nova-act<3.2.0,>=3.1.0; extra == "all"
Requires-Dist: types-aiobotocore-oam<3.2.0,>=3.1.0; extra == "all"
Requires-Dist: types-aiobotocore-observabilityadmin<3.2.0,>=3.1.0; extra == "all"
Requires-Dist: types-aiobotocore-odb<3.2.0,>=3.1.0; extra == "all"
Requires-Dist: types-aiobotocore-omics<3.2.0,>=3.1.0; extra == "all"
Requires-Dist: types-aiobotocore-opensearch<3.2.0,>=3.1.0; extra == "all"
Requires-Dist: types-aiobotocore-opensearchserverless<3.2.0,>=3.1.0; extra == "all"
Requires-Dist: types-aiobotocore-organizations<3.2.0,>=3.1.0; extra == "all"
Requires-Dist: types-aiobotocore-osis<3.2.0,>=3.1.0; extra == "all"
Requires-Dist: types-aiobotocore-outposts<3.2.0,>=3.1.0; extra == "all"
Requires-Dist: types-aiobotocore-panorama<3.2.0,>=3.1.0; extra == "all"
Requires-Dist: types-aiobotocore-partnercentral-account<3.2.0,>=3.1.0; extra == "all"
Requires-Dist: types-aiobotocore-partnercentral-benefits<3.2.0,>=3.1.0; extra == "all"
Requires-Dist: types-aiobotocore-partnercentral-channel<3.2.0,>=3.1.0; extra == "all"
Requires-Dist: types-aiobotocore-partnercentral-selling<3.2.0,>=3.1.0; extra == "all"
Requires-Dist: types-aiobotocore-payment-cryptography<3.2.0,>=3.1.0; extra == "all"
Requires-Dist: types-aiobotocore-payment-cryptography-data<3.2.0,>=3.1.0; extra == "all"
Requires-Dist: types-aiobotocore-pca-connector-ad<3.2.0,>=3.1.0; extra == "all"
Requires-Dist: types-aiobotocore-pca-connector-scep<3.2.0,>=3.1.0; extra == "all"
Requires-Dist: types-aiobotocore-pcs<3.2.0,>=3.1.0; extra == "all"
Requires-Dist: types-aiobotocore-personalize<3.2.0,>=3.1.0; extra == "all"
Requires-Dist: types-aiobotocore-personalize-events<3.2.0,>=3.1.0; extra == "all"
Requires-Dist: types-aiobotocore-personalize-runtime<3.2.0,>=3.1.0; extra == "all"
Requires-Dist: types-aiobotocore-pi<3.2.0,>=3.1.0; extra == "all"
Requires-Dist: types-aiobotocore-pinpoint<3.2.0,>=3.1.0; extra == "all"
Requires-Dist: types-aiobotocore-pinpoint-email<3.2.0,>=3.1.0; extra == "all"
Requires-Dist: types-aiobotocore-pinpoint-sms-voice<3.2.0,>=3.1.0; extra == "all"
Requires-Dist: types-aiobotocore-pinpoint-sms-voice-v2<3.2.0,>=3.1.0; extra == "all"
Requires-Dist: types-aiobotocore-pipes<3.2.0,>=3.1.0; extra == "all"
Requires-Dist: types-aiobotocore-polly<3.2.0,>=3.1.0; extra == "all"
Requires-Dist: types-aiobotocore-pricing<3.2.0,>=3.1.0; extra == "all"
Requires-Dist: types-aiobotocore-proton<3.2.0,>=3.1.0; extra == "all"
Requires-Dist: types-aiobotocore-qapps<3.2.0,>=3.1.0; extra == "all"
Requires-Dist: types-aiobotocore-qbusiness<3.2.0,>=3.1.0; extra == "all"
Requires-Dist: types-aiobotocore-qconnect<3.2.0,>=3.1.0; extra == "all"
Requires-Dist: types-aiobotocore-quicksight<3.2.0,>=3.1.0; extra == "all"
Requires-Dist: types-aiobotocore-ram<3.2.0,>=3.1.0; extra == "all"
Requires-Dist: types-aiobotocore-rbin<3.2.0,>=3.1.0; extra == "all"
Requires-Dist: types-aiobotocore-rds<3.2.0,>=3.1.0; extra == "all"
Requires-Dist: types-aiobotocore-rds-data<3.2.0,>=3.1.0; extra == "all"
Requires-Dist: types-aiobotocore-redshift<3.2.0,>=3.1.0; extra == "all"
Requires-Dist: types-aiobotocore-redshift-data<3.2.0,>=3.1.0; extra == "all"
Requires-Dist: types-aiobotocore-redshift-serverless<3.2.0,>=3.1.0; extra == "all"
Requires-Dist: types-aiobotocore-rekognition<3.2.0,>=3.1.0; extra == "all"
Requires-Dist: types-aiobotocore-repostspace<3.2.0,>=3.1.0; extra == "all"
Requires-Dist: types-aiobotocore-resiliencehub<3.2.0,>=3.1.0; extra == "all"
Requires-Dist: types-aiobotocore-resource-explorer-2<3.2.0,>=3.1.0; extra == "all"
Requires-Dist: types-aiobotocore-resource-groups<3.2.0,>=3.1.0; extra == "all"
Requires-Dist: types-aiobotocore-resourcegroupstaggingapi<3.2.0,>=3.1.0; extra == "all"
Requires-Dist: types-aiobotocore-rolesanywhere<3.2.0,>=3.1.0; extra == "all"
Requires-Dist: types-aiobotocore-route53<3.2.0,>=3.1.0; extra == "all"
Requires-Dist: types-aiobotocore-route53-recovery-cluster<3.2.0,>=3.1.0; extra == "all"
Requires-Dist: types-aiobotocore-route53-recovery-control-config<3.2.0,>=3.1.0; extra == "all"
Requires-Dist: types-aiobotocore-route53-recovery-readiness<3.2.0,>=3.1.0; extra == "all"
Requires-Dist: types-aiobotocore-route53domains<3.2.0,>=3.1.0; extra == "all"
Requires-Dist: types-aiobotocore-route53globalresolver<3.2.0,>=3.1.0; extra == "all"
Requires-Dist: types-aiobotocore-route53profiles<3.2.0,>=3.1.0; extra == "all"
Requires-Dist: types-aiobotocore-route53resolver<3.2.0,>=3.1.0; extra == "all"
Requires-Dist: types-aiobotocore-rtbfabric<3.2.0,>=3.1.0; extra == "all"
Requires-Dist: types-aiobotocore-rum<3.2.0,>=3.1.0; extra == "all"
Requires-Dist: types-aiobotocore-s3<3.2.0,>=3.1.0; extra == "all"
Requires-Dist: types-aiobotocore-s3control<3.2.0,>=3.1.0; extra == "all"
Requires-Dist: types-aiobotocore-s3outposts<3.2.0,>=3.1.0; extra == "all"
Requires-Dist: types-aiobotocore-s3tables<3.2.0,>=3.1.0; extra == "all"
Requires-Dist: types-aiobotocore-s3vectors<3.2.0,>=3.1.0; extra == "all"
Requires-Dist: types-aiobotocore-sagemaker<3.2.0,>=3.1.0; extra == "all"
Requires-Dist: types-aiobotocore-sagemaker-a2i-runtime<3.2.0,>=3.1.0; extra == "all"
Requires-Dist: types-aiobotocore-sagemaker-edge<3.2.0,>=3.1.0; extra == "all"
Requires-Dist: types-aiobotocore-sagemaker-featurestore-runtime<3.2.0,>=3.1.0; extra == "all"
Requires-Dist: types-aiobotocore-sagemaker-geospatial<3.2.0,>=3.1.0; extra == "all"
Requires-Dist: types-aiobotocore-sagemaker-metrics<3.2.0,>=3.1.0; extra == "all"
Requires-Dist: types-aiobotocore-sagemaker-runtime<3.2.0,>=3.1.0; extra == "all"
Requires-Dist: types-aiobotocore-savingsplans<3.2.0,>=3.1.0; extra == "all"
Requires-Dist: types-aiobotocore-scheduler<3.2.0,>=3.1.0; extra == "all"
Requires-Dist: types-aiobotocore-schemas<3.2.0,>=3.1.0; extra == "all"
Requires-Dist: types-aiobotocore-sdb<3.2.0,>=3.1.0; extra == "all"
Requires-Dist: types-aiobotocore-secretsmanager<3.2.0,>=3.1.0; extra == "all"
Requires-Dist: types-aiobotocore-security-ir<3.2.0,>=3.1.0; extra == "all"
Requires-Dist: types-aiobotocore-securityhub<3.2.0,>=3.1.0; extra == "all"
Requires-Dist: types-aiobotocore-securitylake<3.2.0,>=3.1.0; extra == "all"
Requires-Dist: types-aiobotocore-serverlessrepo<3.2.0,>=3.1.0; extra == "all"
Requires-Dist: types-aiobotocore-service-quotas<3.2.0,>=3.1.0; extra == "all"
Requires-Dist: types-aiobotocore-servicecatalog<3.2.0,>=3.1.0; extra == "all"
Requires-Dist: types-aiobotocore-servicecatalog-appregistry<3.2.0,>=3.1.0; extra == "all"
Requires-Dist: types-aiobotocore-servicediscovery<3.2.0,>=3.1.0; extra == "all"
Requires-Dist: types-aiobotocore-ses<3.2.0,>=3.1.0; extra == "all"
Requires-Dist: types-aiobotocore-sesv2<3.2.0,>=3.1.0; extra == "all"
Requires-Dist: types-aiobotocore-shield<3.2.0,>=3.1.0; extra == "all"
Requires-Dist: types-aiobotocore-signer<3.2.0,>=3.1.0; extra == "all"
Requires-Dist: types-aiobotocore-signin<3.2.0,>=3.1.0; extra == "all"
Requires-Dist: types-aiobotocore-simspaceweaver<3.2.0,>=3.1.0; extra == "all"
Requires-Dist: types-aiobotocore-snow-device-management<3.2.0,>=3.1.0; extra == "all"
Requires-Dist: types-aiobotocore-snowball<3.2.0,>=3.1.0; extra == "all"
Requires-Dist: types-aiobotocore-sns<3.2.0,>=3.1.0; extra == "all"
Requires-Dist: types-aiobotocore-socialmessaging<3.2.0,>=3.1.0; extra == "all"
Requires-Dist: types-aiobotocore-sqs<3.2.0,>=3.1.0; extra == "all"
Requires-Dist: types-aiobotocore-ssm<3.2.0,>=3.1.0; extra == "all"
Requires-Dist: types-aiobotocore-ssm-contacts<3.2.0,>=3.1.0; extra == "all"
Requires-Dist: types-aiobotocore-ssm-guiconnect<3.2.0,>=3.1.0; extra == "all"
Requires-Dist: types-aiobotocore-ssm-incidents<3.2.0,>=3.1.0; extra == "all"
Requires-Dist: types-aiobotocore-ssm-quicksetup<3.2.0,>=3.1.0; extra == "all"
Requires-Dist: types-aiobotocore-ssm-sap<3.2.0,>=3.1.0; extra == "all"
Requires-Dist: types-aiobotocore-sso<3.2.0,>=3.1.0; extra == "all"
Requires-Dist: types-aiobotocore-sso-admin<3.2.0,>=3.1.0; extra == "all"
Requires-Dist: types-aiobotocore-sso-oidc<3.2.0,>=3.1.0; extra == "all"
Requires-Dist: types-aiobotocore-stepfunctions<3.2.0,>=3.1.0; extra == "all"
Requires-Dist: types-aiobotocore-storagegateway<3.2.0,>=3.1.0; extra == "all"
Requires-Dist: types-aiobotocore-sts<3.2.0,>=3.1.0; extra == "all"
Requires-Dist: types-aiobotocore-supplychain<3.2.0,>=3.1.0; extra == "all"
Requires-Dist: types-aiobotocore-support<3.2.0,>=3.1.0; extra == "all"
Requires-Dist: types-aiobotocore-support-app<3.2.0,>=3.1.0; extra == "all"
Requires-Dist: types-aiobotocore-swf<3.2.0,>=3.1.0; extra == "all"
Requires-Dist: types-aiobotocore-synthetics<3.2.0,>=3.1.0; extra == "all"
Requires-Dist: types-aiobotocore-taxsettings<3.2.0,>=3.1.0; extra == "all"
Requires-Dist: types-aiobotocore-textract<3.2.0,>=3.1.0; extra == "all"
Requires-Dist: types-aiobotocore-timestream-influxdb<3.2.0,>=3.1.0; extra == "all"
Requires-Dist: types-aiobotocore-timestream-query<3.2.0,>=3.1.0; extra == "all"
Requires-Dist: types-aiobotocore-timestream-write<3.2.0,>=3.1.0; extra == "all"
Requires-Dist: types-aiobotocore-tnb<3.2.0,>=3.1.0; extra == "all"
Requires-Dist: types-aiobotocore-transcribe<3.2.0,>=3.1.0; extra == "all"
Requires-Dist: types-aiobotocore-transfer<3.2.0,>=3.1.0; extra == "all"
Requires-Dist: types-aiobotocore-translate<3.2.0,>=3.1.0; extra == "all"
Requires-Dist: types-aiobotocore-trustedadvisor<3.2.0,>=3.1.0; extra == "all"
Requires-Dist: types-aiobotocore-verifiedpermissions<3.2.0,>=3.1.0; extra == "all"
Requires-Dist: types-aiobotocore-voice-id<3.2.0,>=3.1.0; extra == "all"
Requires-Dist: types-aiobotocore-vpc-lattice<3.2.0,>=3.1.0; extra == "all"
Requires-Dist: types-aiobotocore-waf<3.2.0,>=3.1.0; extra == "all"
Requires-Dist: types-aiobotocore-waf-regional<3.2.0,>=3.1.0; extra == "all"
Requires-Dist: types-aiobotocore-wafv2<3.2.0,>=3.1.0; extra == "all"
Requires-Dist: types-aiobotocore-wellarchitected<3.2.0,>=3.1.0; extra == "all"
Requires-Dist: types-aiobotocore-wickr<3.2.0,>=3.1.0; extra == "all"
Requires-Dist: types-aiobotocore-wisdom<3.2.0,>=3.1.0; extra == "all"
Requires-Dist: types-aiobotocore-workdocs<3.2.0,>=3.1.0; extra == "all"
Requires-Dist: types-aiobotocore-workmail<3.2.0,>=3.1.0; extra == "all"
Requires-Dist: types-aiobotocore-workmailmessageflow<3.2.0,>=3.1.0; extra == "all"
Requires-Dist: types-aiobotocore-workspaces<3.2.0,>=3.1.0; extra == "all"
Requires-Dist: types-aiobotocore-workspaces-instances<3.2.0,>=3.1.0; extra == "all"
Requires-Dist: types-aiobotocore-workspaces-thin-client<3.2.0,>=3.1.0; extra == "all"
Requires-Dist: types-aiobotocore-workspaces-web<3.2.0,>=3.1.0; extra == "all"
Requires-Dist: types-aiobotocore-xray<3.2.0,>=3.1.0; extra == "all"
Provides-Extra: essential
Requires-Dist: types-aiobotocore-cloudformation<3.2.0,>=3.1.0; extra == "essential"
Requires-Dist: types-aiobotocore-dynamodb<3.2.0,>=3.1.0; extra == "essential"
Requires-Dist: types-aiobotocore-ec2<3.2.0,>=3.1.0; extra == "essential"
Requires-Dist: types-aiobotocore-lambda<3.2.0,>=3.1.0; extra == "essential"
Requires-Dist: types-aiobotocore-rds<3.2.0,>=3.1.0; extra == "essential"
Requires-Dist: types-aiobotocore-s3<3.2.0,>=3.1.0; extra == "essential"
Requires-Dist: types-aiobotocore-sqs<3.2.0,>=3.1.0; extra == "essential"
Provides-Extra: accessanalyzer
Requires-Dist: types-aiobotocore-accessanalyzer<3.2.0,>=3.1.0; extra == "accessanalyzer"
Provides-Extra: account
Requires-Dist: types-aiobotocore-account<3.2.0,>=3.1.0; extra == "account"
Provides-Extra: acm
Requires-Dist: types-aiobotocore-acm<3.2.0,>=3.1.0; extra == "acm"
Provides-Extra: acm-pca
Requires-Dist: types-aiobotocore-acm-pca<3.2.0,>=3.1.0; extra == "acm-pca"
Provides-Extra: aiops
Requires-Dist: types-aiobotocore-aiops<3.2.0,>=3.1.0; extra == "aiops"
Provides-Extra: amp
Requires-Dist: types-aiobotocore-amp<3.2.0,>=3.1.0; extra == "amp"
Provides-Extra: amplify
Requires-Dist: types-aiobotocore-amplify<3.2.0,>=3.1.0; extra == "amplify"
Provides-Extra: amplifybackend
Requires-Dist: types-aiobotocore-amplifybackend<3.2.0,>=3.1.0; extra == "amplifybackend"
Provides-Extra: amplifyuibuilder
Requires-Dist: types-aiobotocore-amplifyuibuilder<3.2.0,>=3.1.0; extra == "amplifyuibuilder"
Provides-Extra: apigateway
Requires-Dist: types-aiobotocore-apigateway<3.2.0,>=3.1.0; extra == "apigateway"
Provides-Extra: apigatewaymanagementapi
Requires-Dist: types-aiobotocore-apigatewaymanagementapi<3.2.0,>=3.1.0; extra == "apigatewaymanagementapi"
Provides-Extra: apigatewayv2
Requires-Dist: types-aiobotocore-apigatewayv2<3.2.0,>=3.1.0; extra == "apigatewayv2"
Provides-Extra: appconfig
Requires-Dist: types-aiobotocore-appconfig<3.2.0,>=3.1.0; extra == "appconfig"
Provides-Extra: appconfigdata
Requires-Dist: types-aiobotocore-appconfigdata<3.2.0,>=3.1.0; extra == "appconfigdata"
Provides-Extra: appfabric
Requires-Dist: types-aiobotocore-appfabric<3.2.0,>=3.1.0; extra == "appfabric"
Provides-Extra: appflow
Requires-Dist: types-aiobotocore-appflow<3.2.0,>=3.1.0; extra == "appflow"
Provides-Extra: appintegrations
Requires-Dist: types-aiobotocore-appintegrations<3.2.0,>=3.1.0; extra == "appintegrations"
Provides-Extra: application-autoscaling
Requires-Dist: types-aiobotocore-application-autoscaling<3.2.0,>=3.1.0; extra == "application-autoscaling"
Provides-Extra: application-insights
Requires-Dist: types-aiobotocore-application-insights<3.2.0,>=3.1.0; extra == "application-insights"
Provides-Extra: application-signals
Requires-Dist: types-aiobotocore-application-signals<3.2.0,>=3.1.0; extra == "application-signals"
Provides-Extra: applicationcostprofiler
Requires-Dist: types-aiobotocore-applicationcostprofiler<3.2.0,>=3.1.0; extra == "applicationcostprofiler"
Provides-Extra: appmesh
Requires-Dist: types-aiobotocore-appmesh<3.2.0,>=3.1.0; extra == "appmesh"
Provides-Extra: apprunner
Requires-Dist: types-aiobotocore-apprunner<3.2.0,>=3.1.0; extra == "apprunner"
Provides-Extra: appstream
Requires-Dist: types-aiobotocore-appstream<3.2.0,>=3.1.0; extra == "appstream"
Provides-Extra: appsync
Requires-Dist: types-aiobotocore-appsync<3.2.0,>=3.1.0; extra == "appsync"
Provides-Extra: arc-region-switch
Requires-Dist: types-aiobotocore-arc-region-switch<3.2.0,>=3.1.0; extra == "arc-region-switch"
Provides-Extra: arc-zonal-shift
Requires-Dist: types-aiobotocore-arc-zonal-shift<3.2.0,>=3.1.0; extra == "arc-zonal-shift"
Provides-Extra: artifact
Requires-Dist: types-aiobotocore-artifact<3.2.0,>=3.1.0; extra == "artifact"
Provides-Extra: athena
Requires-Dist: types-aiobotocore-athena<3.2.0,>=3.1.0; extra == "athena"
Provides-Extra: auditmanager
Requires-Dist: types-aiobotocore-auditmanager<3.2.0,>=3.1.0; extra == "auditmanager"
Provides-Extra: autoscaling
Requires-Dist: types-aiobotocore-autoscaling<3.2.0,>=3.1.0; extra == "autoscaling"
Provides-Extra: autoscaling-plans
Requires-Dist: types-aiobotocore-autoscaling-plans<3.2.0,>=3.1.0; extra == "autoscaling-plans"
Provides-Extra: b2bi
Requires-Dist: types-aiobotocore-b2bi<3.2.0,>=3.1.0; extra == "b2bi"
Provides-Extra: backup
Requires-Dist: types-aiobotocore-backup<3.2.0,>=3.1.0; extra == "backup"
Provides-Extra: backup-gateway
Requires-Dist: types-aiobotocore-backup-gateway<3.2.0,>=3.1.0; extra == "backup-gateway"
Provides-Extra: backupsearch
Requires-Dist: types-aiobotocore-backupsearch<3.2.0,>=3.1.0; extra == "backupsearch"
Provides-Extra: batch
Requires-Dist: types-aiobotocore-batch<3.2.0,>=3.1.0; extra == "batch"
Provides-Extra: bcm-dashboards
Requires-Dist: types-aiobotocore-bcm-dashboards<3.2.0,>=3.1.0; extra == "bcm-dashboards"
Provides-Extra: bcm-data-exports
Requires-Dist: types-aiobotocore-bcm-data-exports<3.2.0,>=3.1.0; extra == "bcm-data-exports"
Provides-Extra: bcm-pricing-calculator
Requires-Dist: types-aiobotocore-bcm-pricing-calculator<3.2.0,>=3.1.0; extra == "bcm-pricing-calculator"
Provides-Extra: bcm-recommended-actions
Requires-Dist: types-aiobotocore-bcm-recommended-actions<3.2.0,>=3.1.0; extra == "bcm-recommended-actions"
Provides-Extra: bedrock
Requires-Dist: types-aiobotocore-bedrock<3.2.0,>=3.1.0; extra == "bedrock"
Provides-Extra: bedrock-agent
Requires-Dist: types-aiobotocore-bedrock-agent<3.2.0,>=3.1.0; extra == "bedrock-agent"
Provides-Extra: bedrock-agent-runtime
Requires-Dist: types-aiobotocore-bedrock-agent-runtime<3.2.0,>=3.1.0; extra == "bedrock-agent-runtime"
Provides-Extra: bedrock-agentcore
Requires-Dist: types-aiobotocore-bedrock-agentcore<3.2.0,>=3.1.0; extra == "bedrock-agentcore"
Provides-Extra: bedrock-agentcore-control
Requires-Dist: types-aiobotocore-bedrock-agentcore-control<3.2.0,>=3.1.0; extra == "bedrock-agentcore-control"
Provides-Extra: bedrock-data-automation
Requires-Dist: types-aiobotocore-bedrock-data-automation<3.2.0,>=3.1.0; extra == "bedrock-data-automation"
Provides-Extra: bedrock-data-automation-runtime
Requires-Dist: types-aiobotocore-bedrock-data-automation-runtime<3.2.0,>=3.1.0; extra == "bedrock-data-automation-runtime"
Provides-Extra: bedrock-runtime
Requires-Dist: types-aiobotocore-bedrock-runtime<3.2.0,>=3.1.0; extra == "bedrock-runtime"
Provides-Extra: billing
Requires-Dist: types-aiobotocore-billing<3.2.0,>=3.1.0; extra == "billing"
Provides-Extra: billingconductor
Requires-Dist: types-aiobotocore-billingconductor<3.2.0,>=3.1.0; extra == "billingconductor"
Provides-Extra: braket
Requires-Dist: types-aiobotocore-braket<3.2.0,>=3.1.0; extra == "braket"
Provides-Extra: budgets
Requires-Dist: types-aiobotocore-budgets<3.2.0,>=3.1.0; extra == "budgets"
Provides-Extra: ce
Requires-Dist: types-aiobotocore-ce<3.2.0,>=3.1.0; extra == "ce"
Provides-Extra: chatbot
Requires-Dist: types-aiobotocore-chatbot<3.2.0,>=3.1.0; extra == "chatbot"
Provides-Extra: chime
Requires-Dist: types-aiobotocore-chime<3.2.0,>=3.1.0; extra == "chime"
Provides-Extra: chime-sdk-identity
Requires-Dist: types-aiobotocore-chime-sdk-identity<3.2.0,>=3.1.0; extra == "chime-sdk-identity"
Provides-Extra: chime-sdk-media-pipelines
Requires-Dist: types-aiobotocore-chime-sdk-media-pipelines<3.2.0,>=3.1.0; extra == "chime-sdk-media-pipelines"
Provides-Extra: chime-sdk-meetings
Requires-Dist: types-aiobotocore-chime-sdk-meetings<3.2.0,>=3.1.0; extra == "chime-sdk-meetings"
Provides-Extra: chime-sdk-messaging
Requires-Dist: types-aiobotocore-chime-sdk-messaging<3.2.0,>=3.1.0; extra == "chime-sdk-messaging"
Provides-Extra: chime-sdk-voice
Requires-Dist: types-aiobotocore-chime-sdk-voice<3.2.0,>=3.1.0; extra == "chime-sdk-voice"
Provides-Extra: cleanrooms
Requires-Dist: types-aiobotocore-cleanrooms<3.2.0,>=3.1.0; extra == "cleanrooms"
Provides-Extra: cleanroomsml
Requires-Dist: types-aiobotocore-cleanroomsml<3.2.0,>=3.1.0; extra == "cleanroomsml"
Provides-Extra: cloud9
Requires-Dist: types-aiobotocore-cloud9<3.2.0,>=3.1.0; extra == "cloud9"
Provides-Extra: cloudcontrol
Requires-Dist: types-aiobotocore-cloudcontrol<3.2.0,>=3.1.0; extra == "cloudcontrol"
Provides-Extra: clouddirectory
Requires-Dist: types-aiobotocore-clouddirectory<3.2.0,>=3.1.0; extra == "clouddirectory"
Provides-Extra: cloudformation
Requires-Dist: types-aiobotocore-cloudformation<3.2.0,>=3.1.0; extra == "cloudformation"
Provides-Extra: cloudfront
Requires-Dist: types-aiobotocore-cloudfront<3.2.0,>=3.1.0; extra == "cloudfront"
Provides-Extra: cloudfront-keyvaluestore
Requires-Dist: types-aiobotocore-cloudfront-keyvaluestore<3.2.0,>=3.1.0; extra == "cloudfront-keyvaluestore"
Provides-Extra: cloudhsm
Requires-Dist: types-aiobotocore-cloudhsm<3.2.0,>=3.1.0; extra == "cloudhsm"
Provides-Extra: cloudhsmv2
Requires-Dist: types-aiobotocore-cloudhsmv2<3.2.0,>=3.1.0; extra == "cloudhsmv2"
Provides-Extra: cloudsearch
Requires-Dist: types-aiobotocore-cloudsearch<3.2.0,>=3.1.0; extra == "cloudsearch"
Provides-Extra: cloudsearchdomain
Requires-Dist: types-aiobotocore-cloudsearchdomain<3.2.0,>=3.1.0; extra == "cloudsearchdomain"
Provides-Extra: cloudtrail
Requires-Dist: types-aiobotocore-cloudtrail<3.2.0,>=3.1.0; extra == "cloudtrail"
Provides-Extra: cloudtrail-data
Requires-Dist: types-aiobotocore-cloudtrail-data<3.2.0,>=3.1.0; extra == "cloudtrail-data"
Provides-Extra: cloudwatch
Requires-Dist: types-aiobotocore-cloudwatch<3.2.0,>=3.1.0; extra == "cloudwatch"
Provides-Extra: codeartifact
Requires-Dist: types-aiobotocore-codeartifact<3.2.0,>=3.1.0; extra == "codeartifact"
Provides-Extra: codebuild
Requires-Dist: types-aiobotocore-codebuild<3.2.0,>=3.1.0; extra == "codebuild"
Provides-Extra: codecatalyst
Requires-Dist: types-aiobotocore-codecatalyst<3.2.0,>=3.1.0; extra == "codecatalyst"
Provides-Extra: codecommit
Requires-Dist: types-aiobotocore-codecommit<3.2.0,>=3.1.0; extra == "codecommit"
Provides-Extra: codeconnections
Requires-Dist: types-aiobotocore-codeconnections<3.2.0,>=3.1.0; extra == "codeconnections"
Provides-Extra: codedeploy
Requires-Dist: types-aiobotocore-codedeploy<3.2.0,>=3.1.0; extra == "codedeploy"
Provides-Extra: codeguru-reviewer
Requires-Dist: types-aiobotocore-codeguru-reviewer<3.2.0,>=3.1.0; extra == "codeguru-reviewer"
Provides-Extra: codeguru-security
Requires-Dist: types-aiobotocore-codeguru-security<3.2.0,>=3.1.0; extra == "codeguru-security"
Provides-Extra: codeguruprofiler
Requires-Dist: types-aiobotocore-codeguruprofiler<3.2.0,>=3.1.0; extra == "codeguruprofiler"
Provides-Extra: codepipeline
Requires-Dist: types-aiobotocore-codepipeline<3.2.0,>=3.1.0; extra == "codepipeline"
Provides-Extra: codestar-connections
Requires-Dist: types-aiobotocore-codestar-connections<3.2.0,>=3.1.0; extra == "codestar-connections"
Provides-Extra: codestar-notifications
Requires-Dist: types-aiobotocore-codestar-notifications<3.2.0,>=3.1.0; extra == "codestar-notifications"
Provides-Extra: cognito-identity
Requires-Dist: types-aiobotocore-cognito-identity<3.2.0,>=3.1.0; extra == "cognito-identity"
Provides-Extra: cognito-idp
Requires-Dist: types-aiobotocore-cognito-idp<3.2.0,>=3.1.0; extra == "cognito-idp"
Provides-Extra: cognito-sync
Requires-Dist: types-aiobotocore-cognito-sync<3.2.0,>=3.1.0; extra == "cognito-sync"
Provides-Extra: comprehend
Requires-Dist: types-aiobotocore-comprehend<3.2.0,>=3.1.0; extra == "comprehend"
Provides-Extra: comprehendmedical
Requires-Dist: types-aiobotocore-comprehendmedical<3.2.0,>=3.1.0; extra == "comprehendmedical"
Provides-Extra: compute-optimizer
Requires-Dist: types-aiobotocore-compute-optimizer<3.2.0,>=3.1.0; extra == "compute-optimizer"
Provides-Extra: compute-optimizer-automation
Requires-Dist: types-aiobotocore-compute-optimizer-automation<3.2.0,>=3.1.0; extra == "compute-optimizer-automation"
Provides-Extra: config
Requires-Dist: types-aiobotocore-config<3.2.0,>=3.1.0; extra == "config"
Provides-Extra: connect
Requires-Dist: types-aiobotocore-connect<3.2.0,>=3.1.0; extra == "connect"
Provides-Extra: connect-contact-lens
Requires-Dist: types-aiobotocore-connect-contact-lens<3.2.0,>=3.1.0; extra == "connect-contact-lens"
Provides-Extra: connectcampaigns
Requires-Dist: types-aiobotocore-connectcampaigns<3.2.0,>=3.1.0; extra == "connectcampaigns"
Provides-Extra: connectcampaignsv2
Requires-Dist: types-aiobotocore-connectcampaignsv2<3.2.0,>=3.1.0; extra == "connectcampaignsv2"
Provides-Extra: connectcases
Requires-Dist: types-aiobotocore-connectcases<3.2.0,>=3.1.0; extra == "connectcases"
Provides-Extra: connectparticipant
Requires-Dist: types-aiobotocore-connectparticipant<3.2.0,>=3.1.0; extra == "connectparticipant"
Provides-Extra: controlcatalog
Requires-Dist: types-aiobotocore-controlcatalog<3.2.0,>=3.1.0; extra == "controlcatalog"
Provides-Extra: controltower
Requires-Dist: types-aiobotocore-controltower<3.2.0,>=3.1.0; extra == "controltower"
Provides-Extra: cost-optimization-hub
Requires-Dist: types-aiobotocore-cost-optimization-hub<3.2.0,>=3.1.0; extra == "cost-optimization-hub"
Provides-Extra: cur
Requires-Dist: types-aiobotocore-cur<3.2.0,>=3.1.0; extra == "cur"
Provides-Extra: customer-profiles
Requires-Dist: types-aiobotocore-customer-profiles<3.2.0,>=3.1.0; extra == "customer-profiles"
Provides-Extra: databrew
Requires-Dist: types-aiobotocore-databrew<3.2.0,>=3.1.0; extra == "databrew"
Provides-Extra: dataexchange
Requires-Dist: types-aiobotocore-dataexchange<3.2.0,>=3.1.0; extra == "dataexchange"
Provides-Extra: datapipeline
Requires-Dist: types-aiobotocore-datapipeline<3.2.0,>=3.1.0; extra == "datapipeline"
Provides-Extra: datasync
Requires-Dist: types-aiobotocore-datasync<3.2.0,>=3.1.0; extra == "datasync"
Provides-Extra: datazone
Requires-Dist: types-aiobotocore-datazone<3.2.0,>=3.1.0; extra == "datazone"
Provides-Extra: dax
Requires-Dist: types-aiobotocore-dax<3.2.0,>=3.1.0; extra == "dax"
Provides-Extra: deadline
Requires-Dist: types-aiobotocore-deadline<3.2.0,>=3.1.0; extra == "deadline"
Provides-Extra: detective
Requires-Dist: types-aiobotocore-detective<3.2.0,>=3.1.0; extra == "detective"
Provides-Extra: devicefarm
Requires-Dist: types-aiobotocore-devicefarm<3.2.0,>=3.1.0; extra == "devicefarm"
Provides-Extra: devops-guru
Requires-Dist: types-aiobotocore-devops-guru<3.2.0,>=3.1.0; extra == "devops-guru"
Provides-Extra: directconnect
Requires-Dist: types-aiobotocore-directconnect<3.2.0,>=3.1.0; extra == "directconnect"
Provides-Extra: discovery
Requires-Dist: types-aiobotocore-discovery<3.2.0,>=3.1.0; extra == "discovery"
Provides-Extra: dlm
Requires-Dist: types-aiobotocore-dlm<3.2.0,>=3.1.0; extra == "dlm"
Provides-Extra: dms
Requires-Dist: types-aiobotocore-dms<3.2.0,>=3.1.0; extra == "dms"
Provides-Extra: docdb
Requires-Dist: types-aiobotocore-docdb<3.2.0,>=3.1.0; extra == "docdb"
Provides-Extra: docdb-elastic
Requires-Dist: types-aiobotocore-docdb-elastic<3.2.0,>=3.1.0; extra == "docdb-elastic"
Provides-Extra: drs
Requires-Dist: types-aiobotocore-drs<3.2.0,>=3.1.0; extra == "drs"
Provides-Extra: ds
Requires-Dist: types-aiobotocore-ds<3.2.0,>=3.1.0; extra == "ds"
Provides-Extra: ds-data
Requires-Dist: types-aiobotocore-ds-data<3.2.0,>=3.1.0; extra == "ds-data"
Provides-Extra: dsql
Requires-Dist: types-aiobotocore-dsql<3.2.0,>=3.1.0; extra == "dsql"
Provides-Extra: dynamodb
Requires-Dist: types-aiobotocore-dynamodb<3.2.0,>=3.1.0; extra == "dynamodb"
Provides-Extra: dynamodbstreams
Requires-Dist: types-aiobotocore-dynamodbstreams<3.2.0,>=3.1.0; extra == "dynamodbstreams"
Provides-Extra: ebs
Requires-Dist: types-aiobotocore-ebs<3.2.0,>=3.1.0; extra == "ebs"
Provides-Extra: ec2
Requires-Dist: types-aiobotocore-ec2<3.2.0,>=3.1.0; extra == "ec2"
Provides-Extra: ec2-instance-connect
Requires-Dist: types-aiobotocore-ec2-instance-connect<3.2.0,>=3.1.0; extra == "ec2-instance-connect"
Provides-Extra: ecr
Requires-Dist: types-aiobotocore-ecr<3.2.0,>=3.1.0; extra == "ecr"
Provides-Extra: ecr-public
Requires-Dist: types-aiobotocore-ecr-public<3.2.0,>=3.1.0; extra == "ecr-public"
Provides-Extra: ecs
Requires-Dist: types-aiobotocore-ecs<3.2.0,>=3.1.0; extra == "ecs"
Provides-Extra: efs
Requires-Dist: types-aiobotocore-efs<3.2.0,>=3.1.0; extra == "efs"
Provides-Extra: eks
Requires-Dist: types-aiobotocore-eks<3.2.0,>=3.1.0; extra == "eks"
Provides-Extra: eks-auth
Requires-Dist: types-aiobotocore-eks-auth<3.2.0,>=3.1.0; extra == "eks-auth"
Provides-Extra: elasticache
Requires-Dist: types-aiobotocore-elasticache<3.2.0,>=3.1.0; extra == "elasticache"
Provides-Extra: elasticbeanstalk
Requires-Dist: types-aiobotocore-elasticbeanstalk<3.2.0,>=3.1.0; extra == "elasticbeanstalk"
Provides-Extra: elb
Requires-Dist: types-aiobotocore-elb<3.2.0,>=3.1.0; extra == "elb"
Provides-Extra: elbv2
Requires-Dist: types-aiobotocore-elbv2<3.2.0,>=3.1.0; extra == "elbv2"
Provides-Extra: emr
Requires-Dist: types-aiobotocore-emr<3.2.0,>=3.1.0; extra == "emr"
Provides-Extra: emr-containers
Requires-Dist: types-aiobotocore-emr-containers<3.2.0,>=3.1.0; extra == "emr-containers"
Provides-Extra: emr-serverless
Requires-Dist: types-aiobotocore-emr-serverless<3.2.0,>=3.1.0; extra == "emr-serverless"
Provides-Extra: entityresolution
Requires-Dist: types-aiobotocore-entityresolution<3.2.0,>=3.1.0; extra == "entityresolution"
Provides-Extra: es
Requires-Dist: types-aiobotocore-es<3.2.0,>=3.1.0; extra == "es"
Provides-Extra: events
Requires-Dist: types-aiobotocore-events<3.2.0,>=3.1.0; extra == "events"
Provides-Extra: evidently
Requires-Dist: types-aiobotocore-evidently<3.2.0,>=3.1.0; extra == "evidently"
Provides-Extra: evs
Requires-Dist: types-aiobotocore-evs<3.2.0,>=3.1.0; extra == "evs"
Provides-Extra: finspace
Requires-Dist: types-aiobotocore-finspace<3.2.0,>=3.1.0; extra == "finspace"
Provides-Extra: finspace-data
Requires-Dist: types-aiobotocore-finspace-data<3.2.0,>=3.1.0; extra == "finspace-data"
Provides-Extra: firehose
Requires-Dist: types-aiobotocore-firehose<3.2.0,>=3.1.0; extra == "firehose"
Provides-Extra: fis
Requires-Dist: types-aiobotocore-fis<3.2.0,>=3.1.0; extra == "fis"
Provides-Extra: fms
Requires-Dist: types-aiobotocore-fms<3.2.0,>=3.1.0; extra == "fms"
Provides-Extra: forecast
Requires-Dist: types-aiobotocore-forecast<3.2.0,>=3.1.0; extra == "forecast"
Provides-Extra: forecastquery
Requires-Dist: types-aiobotocore-forecastquery<3.2.0,>=3.1.0; extra == "forecastquery"
Provides-Extra: frauddetector
Requires-Dist: types-aiobotocore-frauddetector<3.2.0,>=3.1.0; extra == "frauddetector"
Provides-Extra: freetier
Requires-Dist: types-aiobotocore-freetier<3.2.0,>=3.1.0; extra == "freetier"
Provides-Extra: fsx
Requires-Dist: types-aiobotocore-fsx<3.2.0,>=3.1.0; extra == "fsx"
Provides-Extra: gamelift
Requires-Dist: types-aiobotocore-gamelift<3.2.0,>=3.1.0; extra == "gamelift"
Provides-Extra: gameliftstreams
Requires-Dist: types-aiobotocore-gameliftstreams<3.2.0,>=3.1.0; extra == "gameliftstreams"
Provides-Extra: geo-maps
Requires-Dist: types-aiobotocore-geo-maps<3.2.0,>=3.1.0; extra == "geo-maps"
Provides-Extra: geo-places
Requires-Dist: types-aiobotocore-geo-places<3.2.0,>=3.1.0; extra == "geo-places"
Provides-Extra: geo-routes
Requires-Dist: types-aiobotocore-geo-routes<3.2.0,>=3.1.0; extra == "geo-routes"
Provides-Extra: glacier
Requires-Dist: types-aiobotocore-glacier<3.2.0,>=3.1.0; extra == "glacier"
Provides-Extra: globalaccelerator
Requires-Dist: types-aiobotocore-globalaccelerator<3.2.0,>=3.1.0; extra == "globalaccelerator"
Provides-Extra: glue
Requires-Dist: types-aiobotocore-glue<3.2.0,>=3.1.0; extra == "glue"
Provides-Extra: grafana
Requires-Dist: types-aiobotocore-grafana<3.2.0,>=3.1.0; extra == "grafana"
Provides-Extra: greengrass
Requires-Dist: types-aiobotocore-greengrass<3.2.0,>=3.1.0; extra == "greengrass"
Provides-Extra: greengrassv2
Requires-Dist: types-aiobotocore-greengrassv2<3.2.0,>=3.1.0; extra == "greengrassv2"
Provides-Extra: groundstation
Requires-Dist: types-aiobotocore-groundstation<3.2.0,>=3.1.0; extra == "groundstation"
Provides-Extra: guardduty
Requires-Dist: types-aiobotocore-guardduty<3.2.0,>=3.1.0; extra == "guardduty"
Provides-Extra: health
Requires-Dist: types-aiobotocore-health<3.2.0,>=3.1.0; extra == "health"
Provides-Extra: healthlake
Requires-Dist: types-aiobotocore-healthlake<3.2.0,>=3.1.0; extra == "healthlake"
Provides-Extra: iam
Requires-Dist: types-aiobotocore-iam<3.2.0,>=3.1.0; extra == "iam"
Provides-Extra: identitystore
Requires-Dist: types-aiobotocore-identitystore<3.2.0,>=3.1.0; extra == "identitystore"
Provides-Extra: imagebuilder
Requires-Dist: types-aiobotocore-imagebuilder<3.2.0,>=3.1.0; extra == "imagebuilder"
Provides-Extra: importexport
Requires-Dist: types-aiobotocore-importexport<3.2.0,>=3.1.0; extra == "importexport"
Provides-Extra: inspector
Requires-Dist: types-aiobotocore-inspector<3.2.0,>=3.1.0; extra == "inspector"
Provides-Extra: inspector-scan
Requires-Dist: types-aiobotocore-inspector-scan<3.2.0,>=3.1.0; extra == "inspector-scan"
Provides-Extra: inspector2
Requires-Dist: types-aiobotocore-inspector2<3.2.0,>=3.1.0; extra == "inspector2"
Provides-Extra: internetmonitor
Requires-Dist: types-aiobotocore-internetmonitor<3.2.0,>=3.1.0; extra == "internetmonitor"
Provides-Extra: invoicing
Requires-Dist: types-aiobotocore-invoicing<3.2.0,>=3.1.0; extra == "invoicing"
Provides-Extra: iot
Requires-Dist: types-aiobotocore-iot<3.2.0,>=3.1.0; extra == "iot"
Provides-Extra: iot-data
Requires-Dist: types-aiobotocore-iot-data<3.2.0,>=3.1.0; extra == "iot-data"
Provides-Extra: iot-jobs-data
Requires-Dist: types-aiobotocore-iot-jobs-data<3.2.0,>=3.1.0; extra == "iot-jobs-data"
Provides-Extra: iot-managed-integrations
Requires-Dist: types-aiobotocore-iot-managed-integrations<3.2.0,>=3.1.0; extra == "iot-managed-integrations"
Provides-Extra: iotanalytics
Requires-Dist: types-aiobotocore-iotanalytics<3.2.0,>=3.1.0; extra == "iotanalytics"
Provides-Extra: iotdeviceadvisor
Requires-Dist: types-aiobotocore-iotdeviceadvisor<3.2.0,>=3.1.0; extra == "iotdeviceadvisor"
Provides-Extra: iotevents
Requires-Dist: types-aiobotocore-iotevents<3.2.0,>=3.1.0; extra == "iotevents"
Provides-Extra: iotevents-data
Requires-Dist: types-aiobotocore-iotevents-data<3.2.0,>=3.1.0; extra == "iotevents-data"
Provides-Extra: iotfleetwise
Requires-Dist: types-aiobotocore-iotfleetwise<3.2.0,>=3.1.0; extra == "iotfleetwise"
Provides-Extra: iotsecuretunneling
Requires-Dist: types-aiobotocore-iotsecuretunneling<3.2.0,>=3.1.0; extra == "iotsecuretunneling"
Provides-Extra: iotsitewise
Requires-Dist: types-aiobotocore-iotsitewise<3.2.0,>=3.1.0; extra == "iotsitewise"
Provides-Extra: iotthingsgraph
Requires-Dist: types-aiobotocore-iotthingsgraph<3.2.0,>=3.1.0; extra == "iotthingsgraph"
Provides-Extra: iottwinmaker
Requires-Dist: types-aiobotocore-iottwinmaker<3.2.0,>=3.1.0; extra == "iottwinmaker"
Provides-Extra: iotwireless
Requires-Dist: types-aiobotocore-iotwireless<3.2.0,>=3.1.0; extra == "iotwireless"
Provides-Extra: ivs
Requires-Dist: types-aiobotocore-ivs<3.2.0,>=3.1.0; extra == "ivs"
Provides-Extra: ivs-realtime
Requires-Dist: types-aiobotocore-ivs-realtime<3.2.0,>=3.1.0; extra == "ivs-realtime"
Provides-Extra: ivschat
Requires-Dist: types-aiobotocore-ivschat<3.2.0,>=3.1.0; extra == "ivschat"
Provides-Extra: kafka
Requires-Dist: types-aiobotocore-kafka<3.2.0,>=3.1.0; extra == "kafka"
Provides-Extra: kafkaconnect
Requires-Dist: types-aiobotocore-kafkaconnect<3.2.0,>=3.1.0; extra == "kafkaconnect"
Provides-Extra: kendra
Requires-Dist: types-aiobotocore-kendra<3.2.0,>=3.1.0; extra == "kendra"
Provides-Extra: kendra-ranking
Requires-Dist: types-aiobotocore-kendra-ranking<3.2.0,>=3.1.0; extra == "kendra-ranking"
Provides-Extra: keyspaces
Requires-Dist: types-aiobotocore-keyspaces<3.2.0,>=3.1.0; extra == "keyspaces"
Provides-Extra: keyspacesstreams
Requires-Dist: types-aiobotocore-keyspacesstreams<3.2.0,>=3.1.0; extra == "keyspacesstreams"
Provides-Extra: kinesis
Requires-Dist: types-aiobotocore-kinesis<3.2.0,>=3.1.0; extra == "kinesis"
Provides-Extra: kinesis-video-archived-media
Requires-Dist: types-aiobotocore-kinesis-video-archived-media<3.2.0,>=3.1.0; extra == "kinesis-video-archived-media"
Provides-Extra: kinesis-video-media
Requires-Dist: types-aiobotocore-kinesis-video-media<3.2.0,>=3.1.0; extra == "kinesis-video-media"
Provides-Extra: kinesis-video-signaling
Requires-Dist: types-aiobotocore-kinesis-video-signaling<3.2.0,>=3.1.0; extra == "kinesis-video-signaling"
Provides-Extra: kinesis-video-webrtc-storage
Requires-Dist: types-aiobotocore-kinesis-video-webrtc-storage<3.2.0,>=3.1.0; extra == "kinesis-video-webrtc-storage"
Provides-Extra: kinesisanalytics
Requires-Dist: types-aiobotocore-kinesisanalytics<3.2.0,>=3.1.0; extra == "kinesisanalytics"
Provides-Extra: kinesisanalyticsv2
Requires-Dist: types-aiobotocore-kinesisanalyticsv2<3.2.0,>=3.1.0; extra == "kinesisanalyticsv2"
Provides-Extra: kinesisvideo
Requires-Dist: types-aiobotocore-kinesisvideo<3.2.0,>=3.1.0; extra == "kinesisvideo"
Provides-Extra: kms
Requires-Dist: types-aiobotocore-kms<3.2.0,>=3.1.0; extra == "kms"
Provides-Extra: lakeformation
Requires-Dist: types-aiobotocore-lakeformation<3.2.0,>=3.1.0; extra == "lakeformation"
Provides-Extra: lambda
Requires-Dist: types-aiobotocore-lambda<3.2.0,>=3.1.0; extra == "lambda"
Provides-Extra: launch-wizard
Requires-Dist: types-aiobotocore-launch-wizard<3.2.0,>=3.1.0; extra == "launch-wizard"
Provides-Extra: lex-models
Requires-Dist: types-aiobotocore-lex-models<3.2.0,>=3.1.0; extra == "lex-models"
Provides-Extra: lex-runtime
Requires-Dist: types-aiobotocore-lex-runtime<3.2.0,>=3.1.0; extra == "lex-runtime"
Provides-Extra: lexv2-models
Requires-Dist: types-aiobotocore-lexv2-models<3.2.0,>=3.1.0; extra == "lexv2-models"
Provides-Extra: lexv2-runtime
Requires-Dist: types-aiobotocore-lexv2-runtime<3.2.0,>=3.1.0; extra == "lexv2-runtime"
Provides-Extra: license-manager
Requires-Dist: types-aiobotocore-license-manager<3.2.0,>=3.1.0; extra == "license-manager"
Provides-Extra: license-manager-linux-subscriptions
Requires-Dist: types-aiobotocore-license-manager-linux-subscriptions<3.2.0,>=3.1.0; extra == "license-manager-linux-subscriptions"
Provides-Extra: license-manager-user-subscriptions
Requires-Dist: types-aiobotocore-license-manager-user-subscriptions<3.2.0,>=3.1.0; extra == "license-manager-user-subscriptions"
Provides-Extra: lightsail
Requires-Dist: types-aiobotocore-lightsail<3.2.0,>=3.1.0; extra == "lightsail"
Provides-Extra: location
Requires-Dist: types-aiobotocore-location<3.2.0,>=3.1.0; extra == "location"
Provides-Extra: logs
Requires-Dist: types-aiobotocore-logs<3.2.0,>=3.1.0; extra == "logs"
Provides-Extra: lookoutequipment
Requires-Dist: types-aiobotocore-lookoutequipment<3.2.0,>=3.1.0; extra == "lookoutequipment"
Provides-Extra: m2
Requires-Dist: types-aiobotocore-m2<3.2.0,>=3.1.0; extra == "m2"
Provides-Extra: machinelearning
Requires-Dist: types-aiobotocore-machinelearning<3.2.0,>=3.1.0; extra == "machinelearning"
Provides-Extra: macie2
Requires-Dist: types-aiobotocore-macie2<3.2.0,>=3.1.0; extra == "macie2"
Provides-Extra: mailmanager
Requires-Dist: types-aiobotocore-mailmanager<3.2.0,>=3.1.0; extra == "mailmanager"
Provides-Extra: managedblockchain
Requires-Dist: types-aiobotocore-managedblockchain<3.2.0,>=3.1.0; extra == "managedblockchain"
Provides-Extra: managedblockchain-query
Requires-Dist: types-aiobotocore-managedblockchain-query<3.2.0,>=3.1.0; extra == "managedblockchain-query"
Provides-Extra: marketplace-agreement
Requires-Dist: types-aiobotocore-marketplace-agreement<3.2.0,>=3.1.0; extra == "marketplace-agreement"
Provides-Extra: marketplace-catalog
Requires-Dist: types-aiobotocore-marketplace-catalog<3.2.0,>=3.1.0; extra == "marketplace-catalog"
Provides-Extra: marketplace-deployment
Requires-Dist: types-aiobotocore-marketplace-deployment<3.2.0,>=3.1.0; extra == "marketplace-deployment"
Provides-Extra: marketplace-entitlement
Requires-Dist: types-aiobotocore-marketplace-entitlement<3.2.0,>=3.1.0; extra == "marketplace-entitlement"
Provides-Extra: marketplace-reporting
Requires-Dist: types-aiobotocore-marketplace-reporting<3.2.0,>=3.1.0; extra == "marketplace-reporting"
Provides-Extra: marketplacecommerceanalytics
Requires-Dist: types-aiobotocore-marketplacecommerceanalytics<3.2.0,>=3.1.0; extra == "marketplacecommerceanalytics"
Provides-Extra: mediaconnect
Requires-Dist: types-aiobotocore-mediaconnect<3.2.0,>=3.1.0; extra == "mediaconnect"
Provides-Extra: mediaconvert
Requires-Dist: types-aiobotocore-mediaconvert<3.2.0,>=3.1.0; extra == "mediaconvert"
Provides-Extra: medialive
Requires-Dist: types-aiobotocore-medialive<3.2.0,>=3.1.0; extra == "medialive"
Provides-Extra: mediapackage
Requires-Dist: types-aiobotocore-mediapackage<3.2.0,>=3.1.0; extra == "mediapackage"
Provides-Extra: mediapackage-vod
Requires-Dist: types-aiobotocore-mediapackage-vod<3.2.0,>=3.1.0; extra == "mediapackage-vod"
Provides-Extra: mediapackagev2
Requires-Dist: types-aiobotocore-mediapackagev2<3.2.0,>=3.1.0; extra == "mediapackagev2"
Provides-Extra: mediastore
Requires-Dist: types-aiobotocore-mediastore<3.2.0,>=3.1.0; extra == "mediastore"
Provides-Extra: mediastore-data
Requires-Dist: types-aiobotocore-mediastore-data<3.2.0,>=3.1.0; extra == "mediastore-data"
Provides-Extra: mediatailor
Requires-Dist: types-aiobotocore-mediatailor<3.2.0,>=3.1.0; extra == "mediatailor"
Provides-Extra: medical-imaging
Requires-Dist: types-aiobotocore-medical-imaging<3.2.0,>=3.1.0; extra == "medical-imaging"
Provides-Extra: memorydb
Requires-Dist: types-aiobotocore-memorydb<3.2.0,>=3.1.0; extra == "memorydb"
Provides-Extra: meteringmarketplace
Requires-Dist: types-aiobotocore-meteringmarketplace<3.2.0,>=3.1.0; extra == "meteringmarketplace"
Provides-Extra: mgh
Requires-Dist: types-aiobotocore-mgh<3.2.0,>=3.1.0; extra == "mgh"
Provides-Extra: mgn
Requires-Dist: types-aiobotocore-mgn<3.2.0,>=3.1.0; extra == "mgn"
Provides-Extra: migration-hub-refactor-spaces
Requires-Dist: types-aiobotocore-migration-hub-refactor-spaces<3.2.0,>=3.1.0; extra == "migration-hub-refactor-spaces"
Provides-Extra: migrationhub-config
Requires-Dist: types-aiobotocore-migrationhub-config<3.2.0,>=3.1.0; extra == "migrationhub-config"
Provides-Extra: migrationhuborchestrator
Requires-Dist: types-aiobotocore-migrationhuborchestrator<3.2.0,>=3.1.0; extra == "migrationhuborchestrator"
Provides-Extra: migrationhubstrategy
Requires-Dist: types-aiobotocore-migrationhubstrategy<3.2.0,>=3.1.0; extra == "migrationhubstrategy"
Provides-Extra: mpa
Requires-Dist: types-aiobotocore-mpa<3.2.0,>=3.1.0; extra == "mpa"
Provides-Extra: mq
Requires-Dist: types-aiobotocore-mq<3.2.0,>=3.1.0; extra == "mq"
Provides-Extra: mturk
Requires-Dist: types-aiobotocore-mturk<3.2.0,>=3.1.0; extra == "mturk"
Provides-Extra: mwaa
Requires-Dist: types-aiobotocore-mwaa<3.2.0,>=3.1.0; extra == "mwaa"
Provides-Extra: mwaa-serverless
Requires-Dist: types-aiobotocore-mwaa-serverless<3.2.0,>=3.1.0; extra == "mwaa-serverless"
Provides-Extra: neptune
Requires-Dist: types-aiobotocore-neptune<3.2.0,>=3.1.0; extra == "neptune"
Provides-Extra: neptune-graph
Requires-Dist: types-aiobotocore-neptune-graph<3.2.0,>=3.1.0; extra == "neptune-graph"
Provides-Extra: neptunedata
Requires-Dist: types-aiobotocore-neptunedata<3.2.0,>=3.1.0; extra == "neptunedata"
Provides-Extra: network-firewall
Requires-Dist: types-aiobotocore-network-firewall<3.2.0,>=3.1.0; extra == "network-firewall"
Provides-Extra: networkflowmonitor
Requires-Dist: types-aiobotocore-networkflowmonitor<3.2.0,>=3.1.0; extra == "networkflowmonitor"
Provides-Extra: networkmanager
Requires-Dist: types-aiobotocore-networkmanager<3.2.0,>=3.1.0; extra == "networkmanager"
Provides-Extra: networkmonitor
Requires-Dist: types-aiobotocore-networkmonitor<3.2.0,>=3.1.0; extra == "networkmonitor"
Provides-Extra: notifications
Requires-Dist: types-aiobotocore-notifications<3.2.0,>=3.1.0; extra == "notifications"
Provides-Extra: notificationscontacts
Requires-Dist: types-aiobotocore-notificationscontacts<3.2.0,>=3.1.0; extra == "notificationscontacts"
Provides-Extra: nova-act
Requires-Dist: types-aiobotocore-nova-act<3.2.0,>=3.1.0; extra == "nova-act"
Provides-Extra: oam
Requires-Dist: types-aiobotocore-oam<3.2.0,>=3.1.0; extra == "oam"
Provides-Extra: observabilityadmin
Requires-Dist: types-aiobotocore-observabilityadmin<3.2.0,>=3.1.0; extra == "observabilityadmin"
Provides-Extra: odb
Requires-Dist: types-aiobotocore-odb<3.2.0,>=3.1.0; extra == "odb"
Provides-Extra: omics
Requires-Dist: types-aiobotocore-omics<3.2.0,>=3.1.0; extra == "omics"
Provides-Extra: opensearch
Requires-Dist: types-aiobotocore-opensearch<3.2.0,>=3.1.0; extra == "opensearch"
Provides-Extra: opensearchserverless
Requires-Dist: types-aiobotocore-opensearchserverless<3.2.0,>=3.1.0; extra == "opensearchserverless"
Provides-Extra: organizations
Requires-Dist: types-aiobotocore-organizations<3.2.0,>=3.1.0; extra == "organizations"
Provides-Extra: osis
Requires-Dist: types-aiobotocore-osis<3.2.0,>=3.1.0; extra == "osis"
Provides-Extra: outposts
Requires-Dist: types-aiobotocore-outposts<3.2.0,>=3.1.0; extra == "outposts"
Provides-Extra: panorama
Requires-Dist: types-aiobotocore-panorama<3.2.0,>=3.1.0; extra == "panorama"
Provides-Extra: partnercentral-account
Requires-Dist: types-aiobotocore-partnercentral-account<3.2.0,>=3.1.0; extra == "partnercentral-account"
Provides-Extra: partnercentral-benefits
Requires-Dist: types-aiobotocore-partnercentral-benefits<3.2.0,>=3.1.0; extra == "partnercentral-benefits"
Provides-Extra: partnercentral-channel
Requires-Dist: types-aiobotocore-partnercentral-channel<3.2.0,>=3.1.0; extra == "partnercentral-channel"
Provides-Extra: partnercentral-selling
Requires-Dist: types-aiobotocore-partnercentral-selling<3.2.0,>=3.1.0; extra == "partnercentral-selling"
Provides-Extra: payment-cryptography
Requires-Dist: types-aiobotocore-payment-cryptography<3.2.0,>=3.1.0; extra == "payment-cryptography"
Provides-Extra: payment-cryptography-data
Requires-Dist: types-aiobotocore-payment-cryptography-data<3.2.0,>=3.1.0; extra == "payment-cryptography-data"
Provides-Extra: pca-connector-ad
Requires-Dist: types-aiobotocore-pca-connector-ad<3.2.0,>=3.1.0; extra == "pca-connector-ad"
Provides-Extra: pca-connector-scep
Requires-Dist: types-aiobotocore-pca-connector-scep<3.2.0,>=3.1.0; extra == "pca-connector-scep"
Provides-Extra: pcs
Requires-Dist: types-aiobotocore-pcs<3.2.0,>=3.1.0; extra == "pcs"
Provides-Extra: personalize
Requires-Dist: types-aiobotocore-personalize<3.2.0,>=3.1.0; extra == "personalize"
Provides-Extra: personalize-events
Requires-Dist: types-aiobotocore-personalize-events<3.2.0,>=3.1.0; extra == "personalize-events"
Provides-Extra: personalize-runtime
Requires-Dist: types-aiobotocore-personalize-runtime<3.2.0,>=3.1.0; extra == "personalize-runtime"
Provides-Extra: pi
Requires-Dist: types-aiobotocore-pi<3.2.0,>=3.1.0; extra == "pi"
Provides-Extra: pinpoint
Requires-Dist: types-aiobotocore-pinpoint<3.2.0,>=3.1.0; extra == "pinpoint"
Provides-Extra: pinpoint-email
Requires-Dist: types-aiobotocore-pinpoint-email<3.2.0,>=3.1.0; extra == "pinpoint-email"
Provides-Extra: pinpoint-sms-voice
Requires-Dist: types-aiobotocore-pinpoint-sms-voice<3.2.0,>=3.1.0; extra == "pinpoint-sms-voice"
Provides-Extra: pinpoint-sms-voice-v2
Requires-Dist: types-aiobotocore-pinpoint-sms-voice-v2<3.2.0,>=3.1.0; extra == "pinpoint-sms-voice-v2"
Provides-Extra: pipes
Requires-Dist: types-aiobotocore-pipes<3.2.0,>=3.1.0; extra == "pipes"
Provides-Extra: polly
Requires-Dist: types-aiobotocore-polly<3.2.0,>=3.1.0; extra == "polly"
Provides-Extra: pricing
Requires-Dist: types-aiobotocore-pricing<3.2.0,>=3.1.0; extra == "pricing"
Provides-Extra: proton
Requires-Dist: types-aiobotocore-proton<3.2.0,>=3.1.0; extra == "proton"
Provides-Extra: qapps
Requires-Dist: types-aiobotocore-qapps<3.2.0,>=3.1.0; extra == "qapps"
Provides-Extra: qbusiness
Requires-Dist: types-aiobotocore-qbusiness<3.2.0,>=3.1.0; extra == "qbusiness"
Provides-Extra: qconnect
Requires-Dist: types-aiobotocore-qconnect<3.2.0,>=3.1.0; extra == "qconnect"
Provides-Extra: quicksight
Requires-Dist: types-aiobotocore-quicksight<3.2.0,>=3.1.0; extra == "quicksight"
Provides-Extra: ram
Requires-Dist: types-aiobotocore-ram<3.2.0,>=3.1.0; extra == "ram"
Provides-Extra: rbin
Requires-Dist: types-aiobotocore-rbin<3.2.0,>=3.1.0; extra == "rbin"
Provides-Extra: rds
Requires-Dist: types-aiobotocore-rds<3.2.0,>=3.1.0; extra == "rds"
Provides-Extra: rds-data
Requires-Dist: types-aiobotocore-rds-data<3.2.0,>=3.1.0; extra == "rds-data"
Provides-Extra: redshift
Requires-Dist: types-aiobotocore-redshift<3.2.0,>=3.1.0; extra == "redshift"
Provides-Extra: redshift-data
Requires-Dist: types-aiobotocore-redshift-data<3.2.0,>=3.1.0; extra == "redshift-data"
Provides-Extra: redshift-serverless
Requires-Dist: types-aiobotocore-redshift-serverless<3.2.0,>=3.1.0; extra == "redshift-serverless"
Provides-Extra: rekognition
Requires-Dist: types-aiobotocore-rekognition<3.2.0,>=3.1.0; extra == "rekognition"
Provides-Extra: repostspace
Requires-Dist: types-aiobotocore-repostspace<3.2.0,>=3.1.0; extra == "repostspace"
Provides-Extra: resiliencehub
Requires-Dist: types-aiobotocore-resiliencehub<3.2.0,>=3.1.0; extra == "resiliencehub"
Provides-Extra: resource-explorer-2
Requires-Dist: types-aiobotocore-resource-explorer-2<3.2.0,>=3.1.0; extra == "resource-explorer-2"
Provides-Extra: resource-groups
Requires-Dist: types-aiobotocore-resource-groups<3.2.0,>=3.1.0; extra == "resource-groups"
Provides-Extra: resourcegroupstaggingapi
Requires-Dist: types-aiobotocore-resourcegroupstaggingapi<3.2.0,>=3.1.0; extra == "resourcegroupstaggingapi"
Provides-Extra: rolesanywhere
Requires-Dist: types-aiobotocore-rolesanywhere<3.2.0,>=3.1.0; extra == "rolesanywhere"
Provides-Extra: route53
Requires-Dist: types-aiobotocore-route53<3.2.0,>=3.1.0; extra == "route53"
Provides-Extra: route53-recovery-cluster
Requires-Dist: types-aiobotocore-route53-recovery-cluster<3.2.0,>=3.1.0; extra == "route53-recovery-cluster"
Provides-Extra: route53-recovery-control-config
Requires-Dist: types-aiobotocore-route53-recovery-control-config<3.2.0,>=3.1.0; extra == "route53-recovery-control-config"
Provides-Extra: route53-recovery-readiness
Requires-Dist: types-aiobotocore-route53-recovery-readiness<3.2.0,>=3.1.0; extra == "route53-recovery-readiness"
Provides-Extra: route53domains
Requires-Dist: types-aiobotocore-route53domains<3.2.0,>=3.1.0; extra == "route53domains"
Provides-Extra: route53globalresolver
Requires-Dist: types-aiobotocore-route53globalresolver<3.2.0,>=3.1.0; extra == "route53globalresolver"
Provides-Extra: route53profiles
Requires-Dist: types-aiobotocore-route53profiles<3.2.0,>=3.1.0; extra == "route53profiles"
Provides-Extra: route53resolver
Requires-Dist: types-aiobotocore-route53resolver<3.2.0,>=3.1.0; extra == "route53resolver"
Provides-Extra: rtbfabric
Requires-Dist: types-aiobotocore-rtbfabric<3.2.0,>=3.1.0; extra == "rtbfabric"
Provides-Extra: rum
Requires-Dist: types-aiobotocore-rum<3.2.0,>=3.1.0; extra == "rum"
Provides-Extra: s3
Requires-Dist: types-aiobotocore-s3<3.2.0,>=3.1.0; extra == "s3"
Provides-Extra: s3control
Requires-Dist: types-aiobotocore-s3control<3.2.0,>=3.1.0; extra == "s3control"
Provides-Extra: s3outposts
Requires-Dist: types-aiobotocore-s3outposts<3.2.0,>=3.1.0; extra == "s3outposts"
Provides-Extra: s3tables
Requires-Dist: types-aiobotocore-s3tables<3.2.0,>=3.1.0; extra == "s3tables"
Provides-Extra: s3vectors
Requires-Dist: types-aiobotocore-s3vectors<3.2.0,>=3.1.0; extra == "s3vectors"
Provides-Extra: sagemaker
Requires-Dist: types-aiobotocore-sagemaker<3.2.0,>=3.1.0; extra == "sagemaker"
Provides-Extra: sagemaker-a2i-runtime
Requires-Dist: types-aiobotocore-sagemaker-a2i-runtime<3.2.0,>=3.1.0; extra == "sagemaker-a2i-runtime"
Provides-Extra: sagemaker-edge
Requires-Dist: types-aiobotocore-sagemaker-edge<3.2.0,>=3.1.0; extra == "sagemaker-edge"
Provides-Extra: sagemaker-featurestore-runtime
Requires-Dist: types-aiobotocore-sagemaker-featurestore-runtime<3.2.0,>=3.1.0; extra == "sagemaker-featurestore-runtime"
Provides-Extra: sagemaker-geospatial
Requires-Dist: types-aiobotocore-sagemaker-geospatial<3.2.0,>=3.1.0; extra == "sagemaker-geospatial"
Provides-Extra: sagemaker-metrics
Requires-Dist: types-aiobotocore-sagemaker-metrics<3.2.0,>=3.1.0; extra == "sagemaker-metrics"
Provides-Extra: sagemaker-runtime
Requires-Dist: types-aiobotocore-sagemaker-runtime<3.2.0,>=3.1.0; extra == "sagemaker-runtime"
Provides-Extra: savingsplans
Requires-Dist: types-aiobotocore-savingsplans<3.2.0,>=3.1.0; extra == "savingsplans"
Provides-Extra: scheduler
Requires-Dist: types-aiobotocore-scheduler<3.2.0,>=3.1.0; extra == "scheduler"
Provides-Extra: schemas
Requires-Dist: types-aiobotocore-schemas<3.2.0,>=3.1.0; extra == "schemas"
Provides-Extra: sdb
Requires-Dist: types-aiobotocore-sdb<3.2.0,>=3.1.0; extra == "sdb"
Provides-Extra: secretsmanager
Requires-Dist: types-aiobotocore-secretsmanager<3.2.0,>=3.1.0; extra == "secretsmanager"
Provides-Extra: security-ir
Requires-Dist: types-aiobotocore-security-ir<3.2.0,>=3.1.0; extra == "security-ir"
Provides-Extra: securityhub
Requires-Dist: types-aiobotocore-securityhub<3.2.0,>=3.1.0; extra == "securityhub"
Provides-Extra: securitylake
Requires-Dist: types-aiobotocore-securitylake<3.2.0,>=3.1.0; extra == "securitylake"
Provides-Extra: serverlessrepo
Requires-Dist: types-aiobotocore-serverlessrepo<3.2.0,>=3.1.0; extra == "serverlessrepo"
Provides-Extra: service-quotas
Requires-Dist: types-aiobotocore-service-quotas<3.2.0,>=3.1.0; extra == "service-quotas"
Provides-Extra: servicecatalog
Requires-Dist: types-aiobotocore-servicecatalog<3.2.0,>=3.1.0; extra == "servicecatalog"
Provides-Extra: servicecatalog-appregistry
Requires-Dist: types-aiobotocore-servicecatalog-appregistry<3.2.0,>=3.1.0; extra == "servicecatalog-appregistry"
Provides-Extra: servicediscovery
Requires-Dist: types-aiobotocore-servicediscovery<3.2.0,>=3.1.0; extra == "servicediscovery"
Provides-Extra: ses
Requires-Dist: types-aiobotocore-ses<3.2.0,>=3.1.0; extra == "ses"
Provides-Extra: sesv2
Requires-Dist: types-aiobotocore-sesv2<3.2.0,>=3.1.0; extra == "sesv2"
Provides-Extra: shield
Requires-Dist: types-aiobotocore-shield<3.2.0,>=3.1.0; extra == "shield"
Provides-Extra: signer
Requires-Dist: types-aiobotocore-signer<3.2.0,>=3.1.0; extra == "signer"
Provides-Extra: signin
Requires-Dist: types-aiobotocore-signin<3.2.0,>=3.1.0; extra == "signin"
Provides-Extra: simspaceweaver
Requires-Dist: types-aiobotocore-simspaceweaver<3.2.0,>=3.1.0; extra == "simspaceweaver"
Provides-Extra: snow-device-management
Requires-Dist: types-aiobotocore-snow-device-management<3.2.0,>=3.1.0; extra == "snow-device-management"
Provides-Extra: snowball
Requires-Dist: types-aiobotocore-snowball<3.2.0,>=3.1.0; extra == "snowball"
Provides-Extra: sns
Requires-Dist: types-aiobotocore-sns<3.2.0,>=3.1.0; extra == "sns"
Provides-Extra: socialmessaging
Requires-Dist: types-aiobotocore-socialmessaging<3.2.0,>=3.1.0; extra == "socialmessaging"
Provides-Extra: sqs
Requires-Dist: types-aiobotocore-sqs<3.2.0,>=3.1.0; extra == "sqs"
Provides-Extra: ssm
Requires-Dist: types-aiobotocore-ssm<3.2.0,>=3.1.0; extra == "ssm"
Provides-Extra: ssm-contacts
Requires-Dist: types-aiobotocore-ssm-contacts<3.2.0,>=3.1.0; extra == "ssm-contacts"
Provides-Extra: ssm-guiconnect
Requires-Dist: types-aiobotocore-ssm-guiconnect<3.2.0,>=3.1.0; extra == "ssm-guiconnect"
Provides-Extra: ssm-incidents
Requires-Dist: types-aiobotocore-ssm-incidents<3.2.0,>=3.1.0; extra == "ssm-incidents"
Provides-Extra: ssm-quicksetup
Requires-Dist: types-aiobotocore-ssm-quicksetup<3.2.0,>=3.1.0; extra == "ssm-quicksetup"
Provides-Extra: ssm-sap
Requires-Dist: types-aiobotocore-ssm-sap<3.2.0,>=3.1.0; extra == "ssm-sap"
Provides-Extra: sso
Requires-Dist: types-aiobotocore-sso<3.2.0,>=3.1.0; extra == "sso"
Provides-Extra: sso-admin
Requires-Dist: types-aiobotocore-sso-admin<3.2.0,>=3.1.0; extra == "sso-admin"
Provides-Extra: sso-oidc
Requires-Dist: types-aiobotocore-sso-oidc<3.2.0,>=3.1.0; extra == "sso-oidc"
Provides-Extra: stepfunctions
Requires-Dist: types-aiobotocore-stepfunctions<3.2.0,>=3.1.0; extra == "stepfunctions"
Provides-Extra: storagegateway
Requires-Dist: types-aiobotocore-storagegateway<3.2.0,>=3.1.0; extra == "storagegateway"
Provides-Extra: sts
Requires-Dist: types-aiobotocore-sts<3.2.0,>=3.1.0; extra == "sts"
Provides-Extra: supplychain
Requires-Dist: types-aiobotocore-supplychain<3.2.0,>=3.1.0; extra == "supplychain"
Provides-Extra: support
Requires-Dist: types-aiobotocore-support<3.2.0,>=3.1.0; extra == "support"
Provides-Extra: support-app
Requires-Dist: types-aiobotocore-support-app<3.2.0,>=3.1.0; extra == "support-app"
Provides-Extra: swf
Requires-Dist: types-aiobotocore-swf<3.2.0,>=3.1.0; extra == "swf"
Provides-Extra: synthetics
Requires-Dist: types-aiobotocore-synthetics<3.2.0,>=3.1.0; extra == "synthetics"
Provides-Extra: taxsettings
Requires-Dist: types-aiobotocore-taxsettings<3.2.0,>=3.1.0; extra == "taxsettings"
Provides-Extra: textract
Requires-Dist: types-aiobotocore-textract<3.2.0,>=3.1.0; extra == "textract"
Provides-Extra: timestream-influxdb
Requires-Dist: types-aiobotocore-timestream-influxdb<3.2.0,>=3.1.0; extra == "timestream-influxdb"
Provides-Extra: timestream-query
Requires-Dist: types-aiobotocore-timestream-query<3.2.0,>=3.1.0; extra == "timestream-query"
Provides-Extra: timestream-write
Requires-Dist: types-aiobotocore-timestream-write<3.2.0,>=3.1.0; extra == "timestream-write"
Provides-Extra: tnb
Requires-Dist: types-aiobotocore-tnb<3.2.0,>=3.1.0; extra == "tnb"
Provides-Extra: transcribe
Requires-Dist: types-aiobotocore-transcribe<3.2.0,>=3.1.0; extra == "transcribe"
Provides-Extra: transfer
Requires-Dist: types-aiobotocore-transfer<3.2.0,>=3.1.0; extra == "transfer"
Provides-Extra: translate
Requires-Dist: types-aiobotocore-translate<3.2.0,>=3.1.0; extra == "translate"
Provides-Extra: trustedadvisor
Requires-Dist: types-aiobotocore-trustedadvisor<3.2.0,>=3.1.0; extra == "trustedadvisor"
Provides-Extra: verifiedpermissions
Requires-Dist: types-aiobotocore-verifiedpermissions<3.2.0,>=3.1.0; extra == "verifiedpermissions"
Provides-Extra: voice-id
Requires-Dist: types-aiobotocore-voice-id<3.2.0,>=3.1.0; extra == "voice-id"
Provides-Extra: vpc-lattice
Requires-Dist: types-aiobotocore-vpc-lattice<3.2.0,>=3.1.0; extra == "vpc-lattice"
Provides-Extra: waf
Requires-Dist: types-aiobotocore-waf<3.2.0,>=3.1.0; extra == "waf"
Provides-Extra: waf-regional
Requires-Dist: types-aiobotocore-waf-regional<3.2.0,>=3.1.0; extra == "waf-regional"
Provides-Extra: wafv2
Requires-Dist: types-aiobotocore-wafv2<3.2.0,>=3.1.0; extra == "wafv2"
Provides-Extra: wellarchitected
Requires-Dist: types-aiobotocore-wellarchitected<3.2.0,>=3.1.0; extra == "wellarchitected"
Provides-Extra: wickr
Requires-Dist: types-aiobotocore-wickr<3.2.0,>=3.1.0; extra == "wickr"
Provides-Extra: wisdom
Requires-Dist: types-aiobotocore-wisdom<3.2.0,>=3.1.0; extra == "wisdom"
Provides-Extra: workdocs
Requires-Dist: types-aiobotocore-workdocs<3.2.0,>=3.1.0; extra == "workdocs"
Provides-Extra: workmail
Requires-Dist: types-aiobotocore-workmail<3.2.0,>=3.1.0; extra == "workmail"
Provides-Extra: workmailmessageflow
Requires-Dist: types-aiobotocore-workmailmessageflow<3.2.0,>=3.1.0; extra == "workmailmessageflow"
Provides-Extra: workspaces
Requires-Dist: types-aiobotocore-workspaces<3.2.0,>=3.1.0; extra == "workspaces"
Provides-Extra: workspaces-instances
Requires-Dist: types-aiobotocore-workspaces-instances<3.2.0,>=3.1.0; extra == "workspaces-instances"
Provides-Extra: workspaces-thin-client
Requires-Dist: types-aiobotocore-workspaces-thin-client<3.2.0,>=3.1.0; extra == "workspaces-thin-client"
Provides-Extra: workspaces-web
Requires-Dist: types-aiobotocore-workspaces-web<3.2.0,>=3.1.0; extra == "workspaces-web"
Provides-Extra: xray
Requires-Dist: types-aiobotocore-xray<3.2.0,>=3.1.0; extra == "xray"
Dynamic: license-file
